[
	{"id":"0001", "gen":1, "variant":1, "name":"Bulbasaur", "type":["grass", "poison"], "special":"starter"},
	{"id":"0002", "gen":1, "variant":1, "name":"Ivysaur", "type":["grass", "poison"]},
	{"id":"0003", "gen":1, "variant":1, "name":"Venusaur", "type":["grass", "poison"]},
	{"id":"0003", "gen":6, "variant":2, "name":"Mega-Venusaur", "type":["grass", "poison"], "special":"megaevo"},
	{"id":"0004", "gen":1, "variant":1, "name":"Charmander", "type":["fire"], "special":"starter"},
	{"id":"0005", "gen":1, "variant":1, "name":"Charmeleon", "type":["fire"]},
	{"id":"0006", "gen":1, "variant":1, "name":"Charizard", "type":["fire", "flying"]},
	{"id":"0006", "gen":6, "variant":2, "name":"Mega-Charizard X", "type":["fire", "dragon"], "special":"megaevo"},
	{"id":"0006", "gen":6, "variant":3, "name":"Mega-Charizard Y", "type":["fire", "flying"], "special":"megaevo"},
	{"id":"0007", "gen":1, "variant":1, "name":"Squirtle", "type":["water"], "special":"starter"},
	{"id":"0008", "gen":1, "variant":1, "name":"Wartortle", "type":["water"]},
	{"id":"0009", "gen":1, "variant":1, "name":"Blastoise", "type":["water"]},
	{"id":"0009", "gen":6, "variant":2, "name":"Mega-Blastoise", "type":["water"], "special":"megaevo"},
	{"id":"0010", "gen":1, "variant":1, "name":"Caterpie", "type":["bug"]},
	{"id":"0011", "gen":1, "variant":1, "name":"Metapod", "type":["bug"]},
	{"id":"0012", "gen":1, "variant":1, "name":"Butterfree", "type":["bug", "flying"]},
	{"id":"0013", "gen":1, "variant":1, "name":"Weedle", "type":["bug", "poison"]},
	{"id":"0014", "gen":1, "variant":1, "name":"Kakuna", "type":["bug", "poison"]},
	{"id":"0015", "gen":1, "variant":1, "name":"Beedrill", "type":["bug", "poison"]},
	{"id":"0015", "gen":6, "variant":2, "name":"Mega-Beedrill", "type":["bug", "poison"], "special":"megaevo"},
	{"id":"0016", "gen":1, "variant":1, "name":"Pidgey", "type":["normal", "flying"]},
	{"id":"0017", "gen":1, "variant":1, "name":"Pidgeotto", "type":["normal", "flying"]},
	{"id":"0018", "gen":1, "variant":1, "name":"Pidgeot", "type":["normal", "flying"]},
	{"id":"0018", "gen":6, "variant":2, "name":"Mega-Pidgeot", "type":["normal", "flying"], "special":"megaevo"},
	{"id":"0019", "gen":1, "variant":1, "name":"Rattata", "type":["normal"]},
	{"id":"0019", "gen":7, "variant":2, "name":"Rattata de Alola", "type":["dark", "normal"], "special":"regional"},
	{"id":"0020", "gen":1, "variant":1, "name":"Raticate", "type":["normal"]},
	{"id":"0020", "gen":7, "variant":2, "name":"Raticate de Alola", "type":["dark", "normal"], "special":"regional"},
	{"id":"0021", "gen":1, "variant":1, "name":"Spearow", "type":["normal", "flying"]},
	{"id":"0022", "gen":1, "variant":1, "name":"Fearow", "type":["normal", "flying"]},
	{"id":"0023", "gen":1, "variant":1, "name":"Ekans", "type":["poison"]},
	{"id":"0024", "gen":1, "variant":1, "name":"Arbok", "type":["poison"]},
	{"id":"0025", "gen":1, "variant":1, "name":"Pikachu", "type":["electric"]},
	{"id":"0026", "gen":1, "variant":1, "name":"Raichu", "type":["electric"]},
	{"id":"0026", "gen":7, "variant":2, "name":"Raichu de Alola", "type":["electric", "psychic"], "special":"regional"},
	{"id":"0027", "gen":1, "variant":1, "name":"Sandshrew", "type":["ground"]},
	{"id":"0027", "gen":7, "variant":2, "name":"Sandshrew de Alola", "type":["ice", "steel"], "special":"regional"},
	{"id":"0028", "gen":1, "variant":1, "name":"Sandslash", "type":["ground"]},
	{"id":"0028", "gen":7, "variant":2, "name":"Sandslash de Alola", "type":["ice", "steel"], "special":"regional"},
	{"id":"0029", "gen":1, "variant":1, "name":"Nidoran♀", "type":["poison"]},
	{"id":"0030", "gen":1, "variant":1, "name":"Nidorina", "type":["poison"]},
	{"id":"0031", "gen":1, "variant":1, "name":"Nidoqueen", "type":["poison", "ground"]},
	{"id":"0032", "gen":1, "variant":1, "name":"Nidoran♂", "type":["poison"]},
	{"id":"0033", "gen":1, "variant":1, "name":"Nidorino", "type":["poison"]},
	{"id":"0034", "gen":1, "variant":1, "name":"Nidoking", "type":["poison", "ground"]},
	{"id":"0035", "gen":1, "variant":1, "name":"Clefairy", "type":["fairy"]},
	{"id":"0036", "gen":1, "variant":1, "name":"Clefable", "type":["fairy"]},
	{"id":"0037", "gen":1, "variant":1, "name":"Vulpix", "type":["fire"]},
	{"id":"0037", "gen":7, "variant":2, "name":"Vulpix de Alola", "type":["ice"], "special":"regional"},
	{"id":"0038", "gen":1, "variant":1, "name":"Ninetales", "type":["fire"]},
	{"id":"0038", "gen":7, "variant":2, "name":"Ninetales de Alola", "type":["ice"], "special":"regional"},
	{"id":"0039", "gen":1, "variant":1, "name":"Jigglypuff", "type":["normal", "fairy"]},
	{"id":"0040", "gen":1, "variant":1, "name":"Wigglytuff", "type":["normal", "fairy"]},
	{"id":"0041", "gen":1, "variant":1, "name":"Zubat", "type":["poison", "flying"]},
	{"id":"0042", "gen":1, "variant":1, "name":"Golbat", "type":["poison", "flying"]},
	{"id":"0043", "gen":1, "variant":1, "name":"Oddish", "type":["grass", "poison"]},
	{"id":"0044", "gen":1, "variant":1, "name":"Gloom", "type":["grass", "poison"]},
	{"id":"0045", "gen":1, "variant":1, "name":"Vileplume", "type":["grass", "poison"]},
	{"id":"0046", "gen":1, "variant":1, "name":"Paras", "type":["bug", "grass"]},
	{"id":"0047", "gen":1, "variant":1, "name":"Parasect", "type":["bug", "grass"]},
	{"id":"0048", "gen":1, "variant":1, "name":"Venonat", "type":["bug", "poison"]},
	{"id":"0049", "gen":1, "variant":1, "name":"Venomoth", "type":["bug", "poison"]},
	{"id":"0050", "gen":1, "variant":1, "name":"Diglett", "type":["ground"]},
	{"id":"0050", "gen":7, "variant":2, "name":"Diglett de Alola", "type":["ground", "steel"], "special":"regional"},
	{"id":"0051", "gen":1, "variant":1, "name":"Dugtrio", "type":["ground"]},
	{"id":"0051", "gen":7, "variant":2, "name":"Dugtrio de Alola", "type":["ground", "steel"], "special":"regional"},
	{"id":"0052", "gen":1, "variant":1, "name":"Meowth", "type":["normal"]},
	{"id":"0052", "gen":7, "variant":2, "name":"Meowth de Alola", "type":["dark"], "special":"regional"},
	{"id":"0052", "gen":8, "variant":3, "name":"Meowth de Galar", "type":["steel"], "special":"regional"},
	{"id":"0053", "gen":1, "variant":1, "name":"Persian", "type":["normal"]},
	{"id":"0053", "gen":7, "variant":2, "name":"Persian de Alola", "type":["dark"], "special":"regional"},
	{"id":"0054", "gen":1, "variant":1, "name":"Psyduck", "type":["water"]},
	{"id":"0055", "gen":1, "variant":1, "name":"Golduck", "type":["water"]},
	{"id":"0056", "gen":1, "variant":1, "name":"Mankey", "type":["fighting"]},
	{"id":"0057", "gen":1, "variant":1, "name":"Primeape", "type":["fighting"]},
	{"id":"0058", "gen":1, "variant":1, "name":"Growlithe", "type":["fire"]},
	{"id":"0058", "gen":8, "variant":2, "name":"Growlithe de Hisui", "type":["fire", "rock"], "special":"regional"},
	{"id":"0059", "gen":1, "variant":1, "name":"Arcanine", "type":["fire"]},
	{"id":"0059", "gen":8, "variant":2, "name":"Arcanine de Hisui", "type":["fire", "rock"], "special":"regional"},
	{"id":"0060", "gen":1, "variant":1, "name":"Poliwag", "type":["water"]},
	{"id":"0061", "gen":1, "variant":1, "name":"Poliwhirl", "type":["water"]},
	{"id":"0062", "gen":1, "variant":1, "name":"Poliwrath", "type":["water", "fighting"]},
	{"id":"0063", "gen":1, "variant":1, "name":"Abra", "type":["psychic"]},
	{"id":"0064", "gen":1, "variant":1, "name":"Kadabra", "type":["psychic"]},
	{"id":"0065", "gen":1, "variant":1, "name":"Alakazam", "type":["psychic"]},
	{"id":"0065", "gen":6, "variant":2, "name":"Mega-Alakazam", "type":["psychic"], "special":"megaevo"},
	{"id":"0066", "gen":1, "variant":1, "name":"Machop", "type":["fighting"]},
	{"id":"0067", "gen":1, "variant":1, "name":"Machoke", "type":["fighting"]},
	{"id":"0068", "gen":1, "variant":1, "name":"Machamp", "type":["fighting"]},
	{"id":"0069", "gen":1, "variant":1, "name":"Bellsprout", "type":["grass", "poison"]},
	{"id":"0070", "gen":1, "variant":1, "name":"Weepinbell", "type":["grass", "poison"]},
	{"id":"0071", "gen":1, "variant":1, "name":"Victreebel", "type":["grass", "poison"]},
	{"id":"0072", "gen":1, "variant":1, "name":"Tentacool", "type":["water", "poison"]},
	{"id":"0073", "gen":1, "variant":1, "name":"Tentacruel", "type":["water", "poison"]},
	{"id":"0074", "gen":1, "variant":1, "name":"Geodude", "type":["rock", "ground"]},
	{"id":"0074", "gen":7, "variant":2, "name":"Geodude de Alola", "type":["rock", "electric"], "special":"regional"},
	{"id":"0075", "gen":1, "variant":1, "name":"Graveler", "type":["rock", "ground"]},
	{"id":"0075", "gen":7, "variant":2, "name":"Graveler de Alola", "type":["rock", "electric"], "special":"regional"},
	{"id":"0076", "gen":1, "variant":1, "name":"Golem", "type":["rock", "ground"]},
	{"id":"0076", "gen":7, "variant":2, "name":"Golem de Alola", "type":["rock", "electric"], "special":"regional"},
	{"id":"0077", "gen":1, "variant":1, "name":"Ponyta", "type":["fire"]},
	{"id":"0077", "gen":8, "variant":2, "name":"Ponyta de Galar", "type":["psychic"], "special":"regional"},
	{"id":"0078", "gen":1, "variant":1, "name":"Rapidash", "type":["fire"]},
	{"id":"0078", "gen":8, "variant":2, "name":"Rapidash de Galar", "type":["psychic", "fairy"], "special":"regional"},
	{"id":"0079", "gen":1, "variant":1, "name":"Slowpoke", "type":["water", "psychic"]},
	{"id":"0079", "gen":8, "variant":2, "name":"Slowpoke de Galar", "type":["psychic"], "special":"regional"},
	{"id":"0080", "gen":1, "variant":1, "name":"Slowbro", "type":["water", "psychic"]},
	{"id":"0080", "gen":6, "variant":2, "name":"Mega-Slowbro", "type":["poison", "psychic"], "special":"megaevo"},
	{"id":"0080", "gen":8, "variant":3, "name":"Slowbro de Galar", "type":["poison", "psychic"], "special":"regional"},
	{"id":"0081", "gen":1, "variant":1, "name":"Magnemite", "type":["electric", "steel"]},
	{"id":"0082", "gen":1, "variant":1, "name":"Magneton", "type":["electric", "steel"]},
	{"id":"0083", "gen":1, "variant":1, "name":"Farfetch’d", "type":["normal", "flying"]},
	{"id":"0083", "gen":8, "variant":2, "name":"Farfetch’d de Galar", "type":["fighting"], "special":"regional"},
	{"id":"0084", "gen":1, "variant":1, "name":"Doduo", "type":["normal", "flying"]},
	{"id":"0085", "gen":1, "variant":1, "name":"Dodrio", "type":["normal", "flying"]},
	{"id":"0086", "gen":1, "variant":1, "name":"Seel", "type":["water"]},
	{"id":"0087", "gen":1, "variant":1, "name":"Dewgong", "type":["water", "ice"]},
	{"id":"0088", "gen":1, "variant":1, "name":"Grimer", "type":["poison"]},
	{"id":"0088", "gen":7, "variant":2, "name":"Grimer de Alola", "type":["poison", "dark"], "special":"regional"},
	{"id":"0089", "gen":1, "variant":1, "name":"Muk", "type":["poison"]},
	{"id":"0089", "gen":7, "variant":2, "name":"Muk de Alola", "type":["poison", "dark"], "special":"regional"},
	{"id":"0090", "gen":1, "variant":1, "name":"Shellder", "type":["water"]},
	{"id":"0091", "gen":1, "variant":1, "name":"Cloyster", "type":["water", "ice"]},
	{"id":"0092", "gen":1, "variant":1, "name":"Gastly", "type":["ghost", "poison"]},
	{"id":"0093", "gen":1, "variant":1, "name":"Haunter", "type":["ghost", "poison"]},
	{"id":"0094", "gen":1, "variant":1, "name":"Gengar", "type":["ghost", "poison"]},
	{"id":"0094", "gen":6, "variant":2, "name":"Mega-Gengar", "type":["ghost", "poison"], "special":"megaevo"},
	{"id":"0095", "gen":1, "variant":1, "name":"Onix", "type":["rock", "ground"]},
	{"id":"0096", "gen":1, "variant":1, "name":"Drowzee", "type":["psychic"]},
	{"id":"0097", "gen":1, "variant":1, "name":"Hypno", "type":["psychic"]},
	{"id":"0098", "gen":1, "variant":1, "name":"Krabby", "type":["water"]},
	{"id":"0099", "gen":1, "variant":1, "name":"Kingler", "type":["water"]},
	{"id":"0100", "gen":1, "variant":1, "name":"Voltorb", "type":["electric"]},
	{"id":"0100", "gen":8, "variant":2, "name":"Voltorb de Hisui", "type":["electric", "grass"], "special":"regional"},
	{"id":"0101", "gen":1, "variant":1, "name":"Electrode", "type":["electric"]},
	{"id":"0101", "gen":8, "variant":2, "name":"Electrode de Hisui", "type":["electric", "grass"], "special":"regional"},
	{"id":"0102", "gen":1, "variant":1, "name":"Exeggcute", "type":["grass", "psychic"]},
	{"id":"0103", "gen":1, "variant":1, "name":"Exeggutor", "type":["grass", "psychic"]},
	{"id":"0103", "gen":7, "variant":2, "name":"Exeggutor de Alola", "type":["grass", "dragon"], "special":"regional"},
	{"id":"0104", "gen":1, "variant":1, "name":"Cubone", "type":["ground"]},
	{"id":"0105", "gen":1, "variant":1, "name":"Marowak", "type":["ground"]},
	{"id":"0105", "gen":7, "variant":2, "name":"Marowak de Alola", "type":["fire", "ghost"], "special":"regional"},
	{"id":"0106", "gen":1, "variant":1, "name":"Hitmonlee", "type":["fighting"]},
	{"id":"0107", "gen":1, "variant":1, "name":"Hitmonchan", "type":["fighting"]},
	{"id":"0108", "gen":1, "variant":1, "name":"Lickitung", "type":["normal"]},
	{"id":"0109", "gen":1, "variant":1, "name":"Koffing", "type":["poison"]},
	{"id":"0110", "gen":1, "variant":1, "name":"Weezing", "type":["poison"]},
	{"id":"0110", "gen":8, "variant":2, "name":"Weezing de Galar", "type":["poison", "fairy"], "special":"regional"},
	{"id":"0111", "gen":1, "variant":1, "name":"Rhyhorn", "type":["ground", "rock"]},
	{"id":"0112", "gen":1, "variant":1, "name":"Rhydon", "type":["ground", "rock"]},
	{"id":"0113", "gen":1, "variant":1, "name":"Chansey", "type":["normal"]},
	{"id":"0114", "gen":1, "variant":1, "name":"Tangela", "type":["grass"]},
	{"id":"0115", "gen":1, "variant":1, "name":"Kangaskhan", "type":["normal"]},
	{"id":"0115", "gen":6, "variant":2, "name":"Mega-Kangaskhan", "type":["normal"], "special":"megaevo"},
	{"id":"0116", "gen":1, "variant":1, "name":"Horsea", "type":["water"]},
	{"id":"0117", "gen":1, "variant":1, "name":"Seadra", "type":["water"]},
	{"id":"0118", "gen":1, "variant":1, "name":"Goldeen", "type":["water"]},
	{"id":"0119", "gen":1, "variant":1, "name":"Seaking", "type":["water"]},
	{"id":"0120", "gen":1, "variant":1, "name":"Staryu", "type":["water"]},
	{"id":"0121", "gen":1, "variant":1, "name":"Starmie", "type":["water", "psychic"]},
	{"id":"0122", "gen":1, "variant":1, "name":"Mr. Mime", "type":["psychic", "fairy"]},
	{"id":"0122", "gen":8, "variant":2, "name":"Mr. Mime de Galar", "type":["ice", "psychic"], "special":"regional"},
	{"id":"0123", "gen":1, "variant":1, "name":"Scyther", "type":["bug", "flying"]},
	{"id":"0124", "gen":1, "variant":1, "name":"Jynx", "type":["ice", "psychic"]},
	{"id":"0125", "gen":1, "variant":1, "name":"Electabuzz", "type":["electric"]},
	{"id":"0126", "gen":1, "variant":1, "name":"Magmar", "type":["fire"]},
	{"id":"0127", "gen":1, "variant":1, "name":"Pinsir", "type":["bug"]},
	{"id":"0127", "gen":6, "variant":2, "name":"Mega-Pinsir", "type":["bug", "flying"], "special":"megaevo"},
	{"id":"0128", "gen":1, "variant":1, "name":"Tauros", "type":["normal"]},
	{"id":"0128", "gen":9, "variant":2, "name":"Tauros de Paldea (combatiente)", "type":["fighting"], "special":"regional"},
	{"id":"0128", "gen":9, "variant":3, "name":"Tauros de Paldea (ardiente)", "type":["fighting", "fire"], "special":"regional"},
	{"id":"0128", "gen":9, "variant":4, "name":"Tauros de Paldea (acuática)", "type":["fighting", "water"], "special":"regional"},
	{"id":"0129", "gen":1, "variant":1, "name":"Magikarp", "type":["water"]},
	{"id":"0130", "gen":1, "variant":1, "name":"Gyarados", "type":["water", "flying"]},
	{"id":"0130", "gen":6, "variant":2, "name":"Mega-Gyarados", "type":["water", "dark"], "special":"megaevo"},
	{"id":"0131", "gen":1, "variant":1, "name":"Lapras", "type":["water", "ice"]},
	{"id":"0132", "gen":1, "variant":1, "name":"Ditto", "type":["normal"]},
	{"id":"0133", "gen":1, "variant":1, "name":"Eevee", "type":["normal"]},
	{"id":"0134", "gen":1, "variant":1, "name":"Vaporeon", "type":["water"]},
	{"id":"0135", "gen":1, "variant":1, "name":"Jolteon", "type":["electric"]},
	{"id":"0136", "gen":1, "variant":1, "name":"Flareon", "type":["fire"]},
	{"id":"0137", "gen":1, "variant":1, "name":"Porygon", "type":["normal"]},
	{"id":"0138", "gen":1, "variant":1, "name":"Omanyte", "type":["rock", "water"]},
	{"id":"0139", "gen":1, "variant":1, "name":"Omastar", "type":["rock", "water"]},
	{"id":"0140", "gen":1, "variant":1, "name":"Kabuto", "type":["rock", "water"]},
	{"id":"0141", "gen":1, "variant":1, "name":"Kabutops", "type":["rock", "water"]},
	{"id":"0142", "gen":1, "variant":1, "name":"Aerodactyl", "type":["rock", "flying"]},
	{"id":"0142", "gen":6, "variant":2, "name":"Mega-Aerodactyl", "type":["rock", "flying"], "special":"megaevo"},
	{"id":"0143", "gen":1, "variant":1, "name":"Snorlax", "type":["normal"]},
	{"id":"0144", "gen":1, "variant":1, "name":"Articuno", "type":["ice", "flying"], "special":"legendary"},
	{"id":"0144", "gen":8, "variant":2, "name":"Articuno de Galar", "type":["psychic", "flying"], "special":"regional"},
	{"id":"0145", "gen":1, "variant":1, "name":"Zapdos", "type":["electric", "flying"], "special":"legendary"},
	{"id":"0145", "gen":8, "variant":2, "name":"Zapdos de Galar", "type":["fighting", "flying"], "special":"regional"},
	{"id":"0146", "gen":1, "variant":1, "name":"Moltres", "type":["fire", "flying"], "special":"legendary"},
	{"id":"0146", "gen":8, "variant":2, "name":"Moltres de Galar", "type":["dark", "flying"], "special":"regional"},
	{"id":"0147", "gen":1, "variant":1, "name":"Dratini", "type":["dragon"]},
	{"id":"0148", "gen":1, "variant":1, "name":"Dragonair", "type":["dragon"]},
	{"id":"0149", "gen":1, "variant":1, "name":"Dragonite", "type":["dragon", "flying"]},
	{"id":"0150", "gen":1, "variant":1, "name":"Mewtwo", "type":["psychic"], "special":"legendary"},
	{"id":"0150", "gen":6, "variant":2, "name":"Mega-Mewtwo X", "type":["psychic", "fighting"], "special":"megaevo"},
	{"id":"0150", "gen":6, "variant":3, "name":"Mega-Mewtwo Y", "type":["psychic"], "special":"megaevo"},
	{"id":"0151", "gen":1, "variant":1, "name":"Mew", "type":["psychic"], "special":"legendary"},

	{"id":"0152", "gen":2, "variant":1, "name":"Chikorita", "type":["grass"], "special":"starter"},
	{"id":"0153", "gen":2, "variant":1, "name":"Bayleef", "type":["grass"]},
	{"id":"0154", "gen":2, "variant":1, "name":"Meganium", "type":["grass"]},
	{"id":"0155", "gen":2, "variant":1, "name":"Cyndaquil", "type":["fire"], "special":"starter"},
	{"id":"0156", "gen":2, "variant":1, "name":"Quilava", "type":["fire"]},
	{"id":"0157", "gen":2, "variant":1, "name":"Typhlosion", "type":["fire"]},
	{"id":"0157", "gen":8, "variant":2, "name":"Typhlosion de Hisui", "type":["fire", "ghost"], "special":"regional"},
	{"id":"0158", "gen":2, "variant":1, "name":"Totodile", "type":["water"], "special":"starter"},
	{"id":"0159", "gen":2, "variant":1, "name":"Croconaw", "type":["water"]},
	{"id":"0160", "gen":2, "variant":1, "name":"Feraligatr", "type":["water"]},
	{"id":"0161", "gen":2, "variant":1, "name":"Sentret", "type":["normal"]},
	{"id":"0162", "gen":2, "variant":1, "name":"Furret", "type":["normal"]},
	{"id":"0163", "gen":2, "variant":1, "name":"Hoothoot", "type":["normal", "flying"]},
	{"id":"0164", "gen":2, "variant":1, "name":"Noctowl", "type":["normal", "flying"]},
	{"id":"0165", "gen":2, "variant":1, "name":"Ledyba", "type":["bug", "flying"]},
	{"id":"0166", "gen":2, "variant":1, "name":"Ledian", "type":["bug", "flying"]},
	{"id":"0167", "gen":2, "variant":1, "name":"Spinarak", "type":["bug", "poison"]},
	{"id":"0168", "gen":2, "variant":1, "name":"Ariados", "type":["bug", "poison"]},
	{"id":"0169", "gen":2, "variant":1, "name":"Crobat", "type":["poison", "flying"]},
	{"id":"0170", "gen":2, "variant":1, "name":"Chinchou", "type":["water", "electric"]},
	{"id":"0171", "gen":2, "variant":1, "name":"Lanturn", "type":["water", "electric"]},
	{"id":"0172", "gen":2, "variant":1, "name":"Pichu", "type":["electric"]},
	{"id":"0173", "gen":2, "variant":1, "name":"Cleffa", "type":["fairy"]},
	{"id":"0174", "gen":2, "variant":1, "name":"Igglybuff", "type":["normal", "fairy"]},
	{"id":"0175", "gen":2, "variant":1, "name":"Togepi", "type":["fairy"]},
	{"id":"0176", "gen":2, "variant":1, "name":"Togetic", "type":["fairy", "flying"]},
	{"id":"0177", "gen":2, "variant":1, "name":"Natu", "type":["psychic", "flying"]},
	{"id":"0178", "gen":2, "variant":1, "name":"Xatu", "type":["psychic", "flying"]},
	{"id":"0179", "gen":2, "variant":1, "name":"Mareep", "type":["electric"]},
	{"id":"0180", "gen":2, "variant":1, "name":"Flaaffy", "type":["electric"]},
	{"id":"0181", "gen":2, "variant":1, "name":"Ampharos", "type":["electric"]},
	{"id":"0181", "gen":6, "variant":2, "name":"Mega-Ampharos", "type":["electric", "dragon"], "special":"megaevo"},
	{"id":"0182", "gen":2, "variant":1, "name":"Bellossom", "type":["grass"]},
	{"id":"0183", "gen":2, "variant":1, "name":"Marill", "type":["water", "fairy"]},
	{"id":"0184", "gen":2, "variant":1, "name":"Azumarill", "type":["water", "fairy"]},
	{"id":"0185", "gen":2, "variant":1, "name":"Sudowoodo", "type":["rock"]},
	{"id":"0186", "gen":2, "variant":1, "name":"Politoed", "type":["water"]},
	{"id":"0187", "gen":2, "variant":1, "name":"Hoppip", "type":["grass", "flying"]},
	{"id":"0188", "gen":2, "variant":1, "name":"Skiploom", "type":["grass", "flying"]},
	{"id":"0189", "gen":2, "variant":1, "name":"Jumpluff", "type":["grass", "flying"]},
	{"id":"0190", "gen":2, "variant":1, "name":"Aipom", "type":["normal"]},
	{"id":"0191", "gen":2, "variant":1, "name":"Sunkern", "type":["grass"]},
	{"id":"0192", "gen":2, "variant":1, "name":"Sunflora", "type":["grass"]},
	{"id":"0193", "gen":2, "variant":1, "name":"Yanma", "type":["bug", "flying"]},
	{"id":"0194", "gen":2, "variant":1, "name":"Wooper", "type":["water", "ground"]},
	{"id":"0194", "gen":9, "variant":2, "name":"Wooper de Paldea", "type":["poison", "ground"], "special":"regional"},
	{"id":"0195", "gen":2, "variant":1, "name":"Quagsire", "type":["water", "ground"]},
	{"id":"0196", "gen":2, "variant":1, "name":"Espeon", "type":["psychic"]},
	{"id":"0197", "gen":2, "variant":1, "name":"Umbreon", "type":["dark"]},
	{"id":"0198", "gen":2, "variant":1, "name":"Murkrow", "type":["dark", "flying"]},
	{"id":"0199", "gen":2, "variant":1, "name":"Slowking", "type":["water", "psychic"]},
	{"id":"0199", "gen":8, "variant":2, "name":"Slowking de Galar", "type":["poison", "psychic"], "special":"regional"},
	{"id":"0200", "gen":2, "variant":1, "name":"Misdreavus", "type":["ghost"]},
	{"id":"0201", "gen":2, "variant":1, "name":"Unown", "type":["psychic"]},
	{"id":"0202", "gen":2, "variant":1, "name":"Wobbuffet", "type":["psychic"]},
	{"id":"0203", "gen":2, "variant":1, "name":"Girafarig", "type":["normal", "psychic"]},
	{"id":"0204", "gen":2, "variant":1, "name":"Pineco", "type":["bug"]},
	{"id":"0205", "gen":2, "variant":1, "name":"Forretress", "type":["bug", "steel"]},
	{"id":"0206", "gen":2, "variant":1, "name":"Dunsparce", "type":["normal"]},
	{"id":"0207", "gen":2, "variant":1, "name":"Gligar", "type":["ground", "flying"]},
	{"id":"0208", "gen":2, "variant":1, "name":"Steelix", "type":["steel", "ground"]},
	{"id":"0208", "gen":6, "variant":2, "name":"Mega-Steelix", "type":["steel", "ground"], "special":"megaevo"},
	{"id":"0209", "gen":2, "variant":1, "name":"Snubbull", "type":["fairy"]},
	{"id":"0210", "gen":2, "variant":1, "name":"Granbull", "type":["fairy"]},
	{"id":"0211", "gen":2, "variant":1, "name":"Qwilfish", "type":["water", "poison"]},
	{"id":"0211", "gen":8, "variant":2, "name":"Qwilfish de Hisui", "type":["dark", "poison"], "special":"regional"},
	{"id":"0212", "gen":2, "variant":1, "name":"Scizor", "type":["bug", "steel"]},
	{"id":"0212", "gen":6, "variant":2, "name":"Mega-Scizor", "type":["bug", "steel"], "special":"megaevo"},
	{"id":"0213", "gen":2, "variant":1, "name":"Shuckle", "type":["bug", "rock"]},
	{"id":"0214", "gen":2, "variant":1, "name":"Heracross", "type":["bug", "fighting"]},
	{"id":"0214", "gen":6, "variant":2, "name":"Mega-Heracross", "type":["bug", "fighting"], "special":"megaevo"},
	{"id":"0215", "gen":2, "variant":1, "name":"Sneasel", "type":["dark", "ice"]},
	{"id":"0215", "gen":8, "variant":2, "name":"Sneasel de Hisui", "type":["fighting", "poison"], "special":"regional"},
	{"id":"0216", "gen":2, "variant":1, "name":"Teddiursa", "type":["normal"]},
	{"id":"0217", "gen":2, "variant":1, "name":"Ursaring", "type":["normal"]},
	{"id":"0218", "gen":2, "variant":1, "name":"Slugma", "type":["fire"]},
	{"id":"0219", "gen":2, "variant":1, "name":"Magcargo", "type":["fire", "rock"]},
	{"id":"0220", "gen":2, "variant":1, "name":"Swinub", "type":["ice", "ground"]},
	{"id":"0221", "gen":2, "variant":1, "name":"Piloswine", "type":["ice", "ground"]},
	{"id":"0222", "gen":2, "variant":1, "name":"Corsola", "type":["water", "rock"]},
	{"id":"0222", "gen":8, "variant":2, "name":"Corsola de Galar", "type":["ghost"], "special":"regional"},
	{"id":"0223", "gen":2, "variant":1, "name":"Remoraid", "type":["water"]},
	{"id":"0224", "gen":2, "variant":1, "name":"Octillery", "type":["water"]},
	{"id":"0225", "gen":2, "variant":1, "name":"Delibird", "type":["ice", "flying"]},
	{"id":"0226", "gen":2, "variant":1, "name":"Mantine", "type":["water", "flying"]},
	{"id":"0227", "gen":2, "variant":1, "name":"Skarmory", "type":["steel", "flying"]},
	{"id":"0228", "gen":2, "variant":1, "name":"Houndour", "type":["dark", "fire"]},
	{"id":"0229", "gen":2, "variant":1, "name":"Houndoom", "type":["dark", "fire"]},
	{"id":"0229", "gen":6, "variant":2, "name":"Mega-Houndoom", "type":["dark", "fire"], "special":"megaevo"},
	{"id":"0230", "gen":2, "variant":1, "name":"Kingdra", "type":["water", "dragon"]},
	{"id":"0231", "gen":2, "variant":1, "name":"Phanpy", "type":["ground"]},
	{"id":"0232", "gen":2, "variant":1, "name":"Donphan", "type":["ground"]},
	{"id":"0233", "gen":2, "variant":1, "name":"Porygon2", "type":["normal"]},
	{"id":"0234", "gen":2, "variant":1, "name":"Stantler", "type":["normal"]},
	{"id":"0235", "gen":2, "variant":1, "name":"Smeargle", "type":["normal"]},
	{"id":"0236", "gen":2, "variant":1, "name":"Tyrogue", "type":["fighting"]},
	{"id":"0237", "gen":2, "variant":1, "name":"Hitmontop", "type":["fighting"]},
	{"id":"0238", "gen":2, "variant":1, "name":"Smoochum", "type":["ice", "psychic"]},
	{"id":"0239", "gen":2, "variant":1, "name":"Elekid", "type":["electric"]},
	{"id":"0240", "gen":2, "variant":1, "name":"Magby", "type":["fire"]},
	{"id":"0241", "gen":2, "variant":1, "name":"Miltank", "type":["normal"]},
	{"id":"0242", "gen":2, "variant":1, "name":"Blissey", "type":["normal"]},
	{"id":"0243", "gen":2, "variant":1, "name":"Raikou", "type":["electric"], "special":"legendary"},
	{"id":"0244", "gen":2, "variant":1, "name":"Entei", "type":["fire"], "special":"legendary"},
	{"id":"0245", "gen":2, "variant":1, "name":"Suicune", "type":["water"], "special":"legendary"},
	{"id":"0246", "gen":2, "variant":1, "name":"Larvitar", "type":["rock", "ground"]},
	{"id":"0247", "gen":2, "variant":1, "name":"Pupitar", "type":["rock", "ground"]},
	{"id":"0248", "gen":2, "variant":1, "name":"Tyranitar", "type":["rock", "dark"]},
	{"id":"0248", "gen":6, "variant":2, "name":"Mega-Tyranitar", "type":["rock", "dark"], "special":"megaevo"},
	{"id":"0249", "gen":2, "variant":1, "name":"Lugia", "type":["psychic", "flying"], "special":"legendary"},
	{"id":"0250", "gen":2, "variant":1, "name":"Ho-Oh", "type":["fire", "flying"], "special":"legendary"},
	{"id":"0251", "gen":2, "variant":1, "name":"Celebi", "type":["psychic", "grass"], "special":"legendary"},

	{"id":"0252", "gen":3, "variant":1, "name":"Treecko", "type":["grass"], "special":"starter"},
	{"id":"0253", "gen":3, "variant":1, "name":"Grovyle", "type":["grass"]},
	{"id":"0254", "gen":3, "variant":1, "name":"Sceptile", "type":["grass"]},
	{"id":"0254", "gen":6, "variant":2, "name":"Mega-Sceptile", "type":["grass", "dragon"], "special":"megaevo"},
	{"id":"0255", "gen":3, "variant":1, "name":"Torchic", "type":["fire"], "special":"starter"},
	{"id":"0256", "gen":3, "variant":1, "name":"Combusken", "type":["fire", "fighting"]},
	{"id":"0257", "gen":3, "variant":1, "name":"Blaziken", "type":["fire", "fighting"]},
	{"id":"0257", "gen":6, "variant":2, "name":"Mega-Blaziken", "type":["fire", "fighting"], "special":"megaevo"},
	{"id":"0258", "gen":3, "variant":1, "name":"Mudkip", "type":["water"], "special":"starter"},
	{"id":"0259", "gen":3, "variant":1, "name":"Marshtomp", "type":["water", "ground"]},
	{"id":"0260", "gen":3, "variant":1, "name":"Swampert", "type":["water", "ground"]},
	{"id":"0260", "gen":6, "variant":2, "name":"Mega-Swampert", "type":["water", "ground"], "special":"megaevo"},
	{"id":"0261", "gen":3, "variant":1, "name":"Poochyena", "type":["dark"]},
	{"id":"0262", "gen":3, "variant":1, "name":"Mightyena", "type":["dark"]},
	{"id":"0263", "gen":3, "variant":1, "name":"Zigzagoon", "type":["normal"]},
	{"id":"0263", "gen":8, "variant":2, "name":"Zigzagoon de Galar", "type":["dark", "normal"], "special":"regional"},
	{"id":"0264", "gen":3, "variant":1, "name":"Linoone", "type":["normal"]},
	{"id":"0264", "gen":8, "variant":2, "name":"Linoone de Galar", "type":["dark", "normal"], "special":"regional"},
	{"id":"0265", "gen":3, "variant":1, "name":"Wurmple", "type":["bug"]},
	{"id":"0266", "gen":3, "variant":1, "name":"Silcoon", "type":["bug"]},
	{"id":"0267", "gen":3, "variant":1, "name":"Beautifly", "type":["bug", "flying"]},
	{"id":"0268", "gen":3, "variant":1, "name":"Cascoon", "type":["bug"]},
	{"id":"0269", "gen":3, "variant":1, "name":"Dustox", "type":["bug", "poison"]},
	{"id":"0270", "gen":3, "variant":1, "name":"Lotad", "type":["water", "grass"]},
	{"id":"0271", "gen":3, "variant":1, "name":"Lombre", "type":["water", "grass"]},
	{"id":"0272", "gen":3, "variant":1, "name":"Ludicolo", "type":["water", "grass"]},
	{"id":"0273", "gen":3, "variant":1, "name":"Seedot", "type":["grass"]},
	{"id":"0274", "gen":3, "variant":1, "name":"Nuzleaf", "type":["grass", "dark"]},
	{"id":"0275", "gen":3, "variant":1, "name":"Shiftry", "type":["grass", "dark"]},
	{"id":"0276", "gen":3, "variant":1, "name":"Taillow", "type":["normal", "flying"]},
	{"id":"0277", "gen":3, "variant":1, "name":"Swellow", "type":["normal", "flying"]},
	{"id":"0278", "gen":3, "variant":1, "name":"Wingull", "type":["water", "flying"]},
	{"id":"0279", "gen":3, "variant":1, "name":"Pelipper", "type":["water", "flying"]},
	{"id":"0280", "gen":3, "variant":1, "name":"Ralts", "type":["psychic", "fairy"]},
	{"id":"0281", "gen":3, "variant":1, "name":"Kirlia", "type":["psychic", "fairy"]},
	{"id":"0282", "gen":3, "variant":1, "name":"Gardevoir", "type":["psychic", "fairy"]},
	{"id":"0282", "gen":6, "variant":2, "name":"Mega-Gardevoir", "type":["psychic", "fairy"], "special":"megaevo"},
	{"id":"0283", "gen":3, "variant":1, "name":"Surskit", "type":["bug", "water"]},
	{"id":"0284", "gen":3, "variant":1, "name":"Masquerain", "type":["bug", "flying"]},
	{"id":"0285", "gen":3, "variant":1, "name":"Shroomish", "type":["grass"]},
	{"id":"0286", "gen":3, "variant":1, "name":"Breloom", "type":["grass", "fighting"]},
	{"id":"0287", "gen":3, "variant":1, "name":"Slakoth", "type":["normal"]},
	{"id":"0288", "gen":3, "variant":1, "name":"Vigoroth", "type":["normal"]},
	{"id":"0289", "gen":3, "variant":1, "name":"Slaking", "type":["normal"]},
	{"id":"0290", "gen":3, "variant":1, "name":"Nincada", "type":["bug", "ground"]},
	{"id":"0291", "gen":3, "variant":1, "name":"Ninjask", "type":["bug", "flying"]},
	{"id":"0292", "gen":3, "variant":1, "name":"Shedinja", "type":["bug", "ghost"]},
	{"id":"0293", "gen":3, "variant":1, "name":"Whismur", "type":["normal"]},
	{"id":"0294", "gen":3, "variant":1, "name":"Loudred", "type":["normal"]},
	{"id":"0295", "gen":3, "variant":1, "name":"Exploud", "type":["normal"]},
	{"id":"0296", "gen":3, "variant":1, "name":"Makuhita", "type":["fighting"]},
	{"id":"0297", "gen":3, "variant":1, "name":"Hariyama", "type":["fighting"]},
	{"id":"0298", "gen":3, "variant":1, "name":"Azurill", "type":["normal", "fairy"]},
	{"id":"0299", "gen":3, "variant":1, "name":"Nosepass", "type":["rock"]},
	{"id":"0300", "gen":3, "variant":1, "name":"Skitty", "type":["normal"]},
	{"id":"0301", "gen":3, "variant":1, "name":"Delcatty", "type":["normal"]},
	{"id":"0302", "gen":3, "variant":1, "name":"Sableye", "type":["dark", "ghost"]},
	{"id":"0302", "gen":6, "variant":2, "name":"Mega-Sableye", "type":["dark", "ghost"], "special":"megaevo"},
	{"id":"0303", "gen":3, "variant":1, "name":"Mawile", "type":["steel", "fairy"]},
	{"id":"0303", "gen":6, "variant":2, "name":"Mega-Mawile", "type":["steel", "fairy"], "special":"megaevo"},
	{"id":"0304", "gen":3, "variant":1, "name":"Aron", "type":["steel", "rock"]},
	{"id":"0305", "gen":3, "variant":1, "name":"Lairon", "type":["steel", "rock"]},
	{"id":"0306", "gen":3, "variant":1, "name":"Aggron", "type":["steel", "rock"]},
	{"id":"0306", "gen":6, "variant":2, "name":"Mega-Aggron", "type":["steel"], "special":"megaevo"},
	{"id":"0307", "gen":3, "variant":1, "name":"Meditite", "type":["fighting", "psychic"]},
	{"id":"0308", "gen":3, "variant":1, "name":"Medicham", "type":["fighting", "psychic"]},
	{"id":"0308", "gen":6, "variant":2, "name":"Mega-Medicham", "type":["fighting", "psychic"], "special":"megaevo"},
	{"id":"0309", "gen":3, "variant":1, "name":"Electrike", "type":["electric"]},
	{"id":"0310", "gen":3, "variant":1, "name":"Manectric", "type":["electric"]},
	{"id":"0310", "gen":6, "variant":2, "name":"Mega-Manectric", "type":["electric"], "special":"megaevo"},
	{"id":"0311", "gen":3, "variant":1, "name":"Plusle", "type":["electric"]},
	{"id":"0312", "gen":3, "variant":1, "name":"Minun", "type":["electric"]},
	{"id":"0313", "gen":3, "variant":1, "name":"Volbeat", "type":["bug"]},
	{"id":"0314", "gen":3, "variant":1, "name":"Illumise", "type":["bug"]},
	{"id":"0315", "gen":3, "variant":1, "name":"Roselia", "type":["grass", "poison"]},
	{"id":"0316", "gen":3, "variant":1, "name":"Gulpin", "type":["poison"]},
	{"id":"0317", "gen":3, "variant":1, "name":"Swalot", "type":["poison"]},
	{"id":"0318", "gen":3, "variant":1, "name":"Carvanha", "type":["water", "dark"]},
	{"id":"0319", "gen":3, "variant":1, "name":"Sharpedo", "type":["water", "dark"]},
	{"id":"0319", "gen":6, "variant":2, "name":"Mega-Sharpedo", "type":["water", "dark"], "special":"megaevo"},
	{"id":"0320", "gen":3, "variant":1, "name":"Wailmer", "type":["water"]},
	{"id":"0321", "gen":3, "variant":1, "name":"Wailord", "type":["water"]},
	{"id":"0322", "gen":3, "variant":1, "name":"Numel", "type":["fire", "ground"]},
	{"id":"0323", "gen":3, "variant":1, "name":"Camerupt", "type":["fire", "ground"]},
	{"id":"0323", "gen":6, "variant":2, "name":"Mega-Camerupt", "type":["fire", "ground"], "special":"megaevo"},
	{"id":"0324", "gen":3, "variant":1, "name":"Torkoal", "type":["fire"]},
	{"id":"0325", "gen":3, "variant":1, "name":"Spoink", "type":["psychic"]},
	{"id":"0326", "gen":3, "variant":1, "name":"Grumpig", "type":["psychic"]},
	{"id":"0327", "gen":3, "variant":1, "name":"Spinda", "type":["normal"]},
	{"id":"0328", "gen":3, "variant":1, "name":"Trapinch", "type":["ground"]},
	{"id":"0329", "gen":3, "variant":1, "name":"Vibrava", "type":["ground", "dragon"]},
	{"id":"0330", "gen":3, "variant":1, "name":"Flygon", "type":["ground", "dragon"]},
	{"id":"0331", "gen":3, "variant":1, "name":"Cacnea", "type":["grass"]},
	{"id":"0332", "gen":3, "variant":1, "name":"Cacturne", "type":["grass", "dark"]},
	{"id":"0333", "gen":3, "variant":1, "name":"Swablu", "type":["normal", "flying"]},
	{"id":"0334", "gen":3, "variant":1, "name":"Altaria", "type":["dragon", "flying"]},
	{"id":"0334", "gen":6, "variant":2, "name":"Mega-Altaria", "type":["dragon", "fairy"], "special":"megaevo"},
	{"id":"0335", "gen":3, "variant":1, "name":"Zangoose", "type":["normal"]},
	{"id":"0336", "gen":3, "variant":1, "name":"Seviper", "type":["poison"]},
	{"id":"0337", "gen":3, "variant":1, "name":"Lunatone", "type":["rock", "psychic"]},
	{"id":"0338", "gen":3, "variant":1, "name":"Solrock", "type":["rock", "psychic"]},
	{"id":"0339", "gen":3, "variant":1, "name":"Barboach", "type":["water", "ground"]},
	{"id":"0340", "gen":3, "variant":1, "name":"Whiscash", "type":["water", "ground"]},
	{"id":"0341", "gen":3, "variant":1, "name":"Corphish", "type":["water"]},
	{"id":"0342", "gen":3, "variant":1, "name":"Crawdaunt", "type":["water", "dark"]},
	{"id":"0343", "gen":3, "variant":1, "name":"Baltoy", "type":["ground", "psychic"]},
	{"id":"0344", "gen":3, "variant":1, "name":"Claydol", "type":["ground", "psychic"]},
	{"id":"0345", "gen":3, "variant":1, "name":"Lileep", "type":["rock", "grass"]},
	{"id":"0346", "gen":3, "variant":1, "name":"Cradily", "type":["rock", "grass"]},
	{"id":"0347", "gen":3, "variant":1, "name":"Anorith", "type":["rock", "bug"]},
	{"id":"0348", "gen":3, "variant":1, "name":"Armaldo", "type":["rock", "bug"]},
	{"id":"0349", "gen":3, "variant":1, "name":"Feebas", "type":["water"]},
	{"id":"0350", "gen":3, "variant":1, "name":"Milotic", "type":["water"]},
	{"id":"0351", "gen":3, "variant":1, "name":"Castform", "type":["normal"]},
	{"id":"0352", "gen":3, "variant":1, "name":"Kecleon", "type":["normal"]},
	{"id":"0353", "gen":3, "variant":1, "name":"Shuppet", "type":["ghost"]},
	{"id":"0354", "gen":3, "variant":1, "name":"Banette", "type":["ghost"]},
	{"id":"0354", "gen":6, "variant":2, "name":"Mega-Banette", "type":["ghost"], "special":"megaevo"},
	{"id":"0355", "gen":3, "variant":1, "name":"Duskull", "type":["ghost"]},
	{"id":"0356", "gen":3, "variant":1, "name":"Dusclops", "type":["ghost"]},
	{"id":"0357", "gen":3, "variant":1, "name":"Tropius", "type":["grass", "flying"]},
	{"id":"0358", "gen":3, "variant":1, "name":"Chimecho", "type":["psychic"]},
	{"id":"0359", "gen":3, "variant":1, "name":"Absol", "type":["dark"]},
	{"id":"0359", "gen":6, "variant":2, "name":"Mega-Absol", "type":["dark"], "special":"megaevo"},
	{"id":"0360", "gen":3, "variant":1, "name":"Wynaut", "type":["psychic"]},
	{"id":"0361", "gen":3, "variant":1, "name":"Snorunt", "type":["ice"]},
	{"id":"0362", "gen":3, "variant":1, "name":"Glalie", "type":["ice"]},
	{"id":"0362", "gen":6, "variant":2, "name":"Mega-Glalie", "type":["ice"], "special":"megaevo"},
	{"id":"0363", "gen":3, "variant":1, "name":"Spheal", "type":["ice", "water"]},
	{"id":"0364", "gen":3, "variant":1, "name":"Sealeo", "type":["ice", "water"]},
	{"id":"0365", "gen":3, "variant":1, "name":"Walrein", "type":["ice", "water"]},
	{"id":"0366", "gen":3, "variant":1, "name":"Clamperl", "type":["water"]},
	{"id":"0367", "gen":3, "variant":1, "name":"Huntail", "type":["water"]},
	{"id":"0368", "gen":3, "variant":1, "name":"Gorebyss", "type":["water"]},
	{"id":"0369", "gen":3, "variant":1, "name":"Relicanth", "type":["water", "rock"]},
	{"id":"0370", "gen":3, "variant":1, "name":"Luvdisc", "type":["water"]},
	{"id":"0371", "gen":3, "variant":1, "name":"Bagon", "type":["dragon"]},
	{"id":"0372", "gen":3, "variant":1, "name":"Shelgon", "type":["dragon"]},
	{"id":"0373", "gen":3, "variant":1, "name":"Salamence", "type":["dragon", "flying"]},
	{"id":"0373", "gen":6, "variant":2, "name":"Mega-Salamence", "type":["dragon", "flying"], "special":"megaevo"},
	{"id":"0374", "gen":3, "variant":1, "name":"Beldum", "type":["steel", "psychic"]},
	{"id":"0375", "gen":3, "variant":1, "name":"Metang", "type":["steel", "psychic"]},
	{"id":"0376", "gen":3, "variant":1, "name":"Metagross", "type":["steel", "psychic"]},
	{"id":"0376", "gen":6, "variant":2, "name":"Mega-Metagross", "type":["steel", "psychic"], "special":"megaevo"},
	{"id":"0377", "gen":3, "variant":1, "name":"Regirock", "type":["rock"], "special":"legendary"},
	{"id":"0378", "gen":3, "variant":1, "name":"Regice", "type":["ice"], "special":"legendary"},
	{"id":"0379", "gen":3, "variant":1, "name":"Registeel", "type":["steel"], "special":"legendary"},
	{"id":"0380", "gen":3, "variant":1, "name":"Latias", "type":["dragon", "psychic"], "special":"legendary"},
	{"id":"0380", "gen":6, "variant":2, "name":"Mega-Latias", "type":["dragon", "psychic"], "special":"megaevo"},
	{"id":"0381", "gen":3, "variant":1, "name":"Latios", "type":["dragon", "psychic"], "special":"legendary"},
	{"id":"0381", "gen":6, "variant":2, "name":"Mega-Latios", "type":["dragon", "psychic"], "special":"megaevo"},
	{"id":"0382", "gen":3, "variant":1, "name":"Kyogre", "type":["water"], "special":"legendary"},
	{"id":"0383", "gen":3, "variant":1, "name":"Groudon", "type":["ground"], "special":"legendary"},
	{"id":"0384", "gen":3, "variant":1, "name":"Rayquaza", "type":["dragon", "flying"], "special":"legendary"},
	{"id":"0384", "gen":6, "variant":2, "name":"Mega-Rayquaza", "type":["dragon", "flying"], "special":"megaevo"},
	{"id":"0385", "gen":3, "variant":1, "name":"Jirachi", "type":["steel", "psychic"], "special":"legendary"},
	{"id":"0386", "gen":3, "variant":1, "name":"Deoxys", "type":["psychic"], "special":"legendary"},
	{"id":"0386", "gen":3, "variant":2, "name":"Deoxys (Ataque)", "type":["psychic"], "special":"legendary"},
	{"id":"0386", "gen":3, "variant":3, "name":"Deoxys (Defensa)", "type":["psychic"], "special":"legendary"},
	{"id":"0386", "gen":3, "variant":4, "name":"Deoxys (Velocidad)", "type":["psychic"], "special":"legendary"},

	{"id":"0387", "gen":4, "variant":1, "name":"Turtwig", "type":["grass"], "special":"starter"},
	{"id":"0388", "gen":4, "variant":1, "name":"Grotle", "type":["grass"]},
	{"id":"0389", "gen":4, "variant":1, "name":"Torterra", "type":["grass", "ground"]},
	{"id":"0390", "gen":4, "variant":1, "name":"Chimchar", "type":["fire"], "special":"starter"},
	{"id":"0391", "gen":4, "variant":1, "name":"Monferno", "type":["fire", "fighting"]},
	{"id":"0392", "gen":4, "variant":1, "name":"Infernape", "type":["fire", "fighting"]},
	{"id":"0393", "gen":4, "variant":1, "name":"Piplup", "type":["water"], "special":"starter"},
	{"id":"0394", "gen":4, "variant":1, "name":"Prinplup", "type":["water"]},
	{"id":"0395", "gen":4, "variant":1, "name":"Empoleon", "type":["water", "steel"]},
	{"id":"0396", "gen":4, "variant":1, "name":"Starly", "type":["normal", "flying"]},
	{"id":"0397", "gen":4, "variant":1, "name":"Staravia", "type":["normal", "flying"]},
	{"id":"0398", "gen":4, "variant":1, "name":"Staraptor", "type":["normal", "flying"]},
	{"id":"0399", "gen":4, "variant":1, "name":"Bidoof", "type":["normal"]},
	{"id":"0400", "gen":4, "variant":1, "name":"Bibarel", "type":["normal", "water"]},
	{"id":"0401", "gen":4, "variant":1, "name":"Kricketot", "type":["bug"]},
	{"id":"0402", "gen":4, "variant":1, "name":"Kricketune", "type":["bug"]},
	{"id":"0403", "gen":4, "variant":1, "name":"Shinx", "type":["electric"]},
	{"id":"0404", "gen":4, "variant":1, "name":"Luxio", "type":["electric"]},
	{"id":"0405", "gen":4, "variant":1, "name":"Luxray", "type":["electric"]},
	{"id":"0406", "gen":4, "variant":1, "name":"Budew", "type":["grass", "poison"]},
	{"id":"0407", "gen":4, "variant":1, "name":"Roserade", "type":["grass", "poison"]},
	{"id":"0408", "gen":4, "variant":1, "name":"Cranidos", "type":["rock"]},
	{"id":"0409", "gen":4, "variant":1, "name":"Rampardos", "type":["rock"]},
	{"id":"0410", "gen":4, "variant":1, "name":"Shieldon", "type":["rock", "steel"]},
	{"id":"0411", "gen":4, "variant":1, "name":"Bastiodon", "type":["rock", "steel"]},
	{"id":"0412", "gen":4, "variant":1, "name":"Burmy Planta", "type":["bug"]},
	{"id":"0412", "gen":4, "variant":2, "name":"Burmy Arena", "type":["bug"]},
	{"id":"0412", "gen":4, "variant":3, "name":"Burmy Basura", "type":["bug"]},
	{"id":"0413", "gen":4, "variant":1, "name":"Wormadam Planta", "type":["bug", "grass"]},
	{"id":"0413", "gen":4, "variant":2, "name":"Wormadam Arena", "type":["bug", "ground"]},
	{"id":"0413", "gen":4, "variant":3, "name":"Wormadam Basura", "type":["bug", "steel"]},
	{"id":"0414", "gen":4, "variant":1, "name":"Mothim", "type":["bug", "flying"]},
	{"id":"0415", "gen":4, "variant":1, "name":"Combee", "type":["bug", "flying"]},
	{"id":"0416", "gen":4, "variant":1, "name":"Vespiquen", "type":["bug", "flying"]},
	{"id":"0417", "gen":4, "variant":1, "name":"Pachirisu", "type":["electric"]},
	{"id":"0418", "gen":4, "variant":1, "name":"Buizel", "type":["water"]},
	{"id":"0419", "gen":4, "variant":1, "name":"Floatzel", "type":["water"]},
	{"id":"0420", "gen":4, "variant":1, "name":"Cherubi", "type":["grass"]},
	{"id":"0421", "gen":4, "variant":1, "name":"Cherrim", "type":["grass"]},
	{"id":"0422", "gen":4, "variant":1, "name":"Shellos", "type":["water"]},
	{"id":"0423", "gen":4, "variant":1, "name":"Gastrodon", "type":["water", "ground"]},
	{"id":"0424", "gen":4, "variant":1, "name":"Ambipom", "type":["normal"]},
	{"id":"0425", "gen":4, "variant":1, "name":"Drifloon", "type":["ghost", "flying"]},
	{"id":"0426", "gen":4, "variant":1, "name":"Drifblim", "type":["ghost", "flying"]},
	{"id":"0427", "gen":4, "variant":1, "name":"Buneary", "type":["normal"]},
	{"id":"0428", "gen":4, "variant":1, "name":"Lopunny", "type":["normal"]},
	{"id":"0428", "gen":6, "variant":2, "name":"Mega-Lopunny", "type":["normal", "fighting"], "special":"megaevo"},
	{"id":"0429", "gen":4, "variant":1, "name":"Mismagius", "type":["ghost"]},
	{"id":"0430", "gen":4, "variant":1, "name":"Honchkrow", "type":["dark", "flying"]},
	{"id":"0431", "gen":4, "variant":1, "name":"Glameow", "type":["normal"]},
	{"id":"0432", "gen":4, "variant":1, "name":"Purugly", "type":["normal"]},
	{"id":"0433", "gen":4, "variant":1, "name":"Chingling", "type":["psychic"]},
	{"id":"0434", "gen":4, "variant":1, "name":"Stunky", "type":["poison", "dark"]},
	{"id":"0435", "gen":4, "variant":1, "name":"Skuntank", "type":["poison", "dark"]},
	{"id":"0436", "gen":4, "variant":1, "name":"Bronzor", "type":["steel", "psychic"]},
	{"id":"0437", "gen":4, "variant":1, "name":"Bronzong", "type":["steel", "psychic"]},
	{"id":"0438", "gen":4, "variant":1, "name":"Bonsly", "type":["rock"]},
	{"id":"0439", "gen":4, "variant":1, "name":"Mime Jr.", "type":["psychic", "fairy"]},
	{"id":"0440", "gen":4, "variant":1, "name":"Happiny", "type":["normal"]},
	{"id":"0441", "gen":4, "variant":1, "name":"Chatot", "type":["normal", "flying"]},
	{"id":"0442", "gen":4, "variant":1, "name":"Spiritomb", "type":["ghost", "dark"]},
	{"id":"0443", "gen":4, "variant":1, "name":"Gible", "type":["dragon", "ground"]},
	{"id":"0444", "gen":4, "variant":1, "name":"Gabite", "type":["dragon", "ground"]},
	{"id":"0445", "gen":4, "variant":1, "name":"Garchomp", "type":["dragon", "ground"]},
	{"id":"0445", "gen":6, "variant":2, "name":"Mega-Garchomp", "type":["dragon", "ground"], "special":"megaevo"},
	{"id":"0446", "gen":4, "variant":1, "name":"Munchlax", "type":["normal"]},
	{"id":"0447", "gen":4, "variant":1, "name":"Riolu", "type":["fighting"]},
	{"id":"0448", "gen":4, "variant":1, "name":"Lucario", "type":["fighting", "steel"]},
	{"id":"0448", "gen":6, "variant":2, "name":"Mega-Lucario", "type":["fighting", "steel"], "special":"megaevo"},
	{"id":"0449", "gen":4, "variant":1, "name":"Hippopotas", "type":["ground"]},
	{"id":"0450", "gen":4, "variant":1, "name":"Hippowdon", "type":["ground"]},
	{"id":"0451", "gen":4, "variant":1, "name":"Skorupi", "type":["poison", "bug"]},
	{"id":"0452", "gen":4, "variant":1, "name":"Drapion", "type":["poison", "dark"]},
	{"id":"0453", "gen":4, "variant":1, "name":"Croagunk", "type":["poison", "fighting"]},
	{"id":"0454", "gen":4, "variant":1, "name":"Toxicroak", "type":["poison", "fighting"]},
	{"id":"0455", "gen":4, "variant":1, "name":"Carnivine", "type":["grass"]},
	{"id":"0456", "gen":4, "variant":1, "name":"Finneon", "type":["water"]},
	{"id":"0457", "gen":4, "variant":1, "name":"Lumineon", "type":["water"]},
	{"id":"0458", "gen":4, "variant":1, "name":"Mantyke", "type":["water", "flying"]},
	{"id":"0459", "gen":4, "variant":1, "name":"Snover", "type":["grass", "ice"]},
	{"id":"0460", "gen":4, "variant":1, "name":"Abomasnow", "type":["grass", "ice"]},
	{"id":"0460", "gen":6, "variant":2, "name":"Mega-Abomasnow", "type":["grass", "ice"], "special":"megaevo"},
	{"id":"0461", "gen":4, "variant":1, "name":"Weavile", "type":["dark", "ice"]},
	{"id":"0462", "gen":4, "variant":1, "name":"Magnezone", "type":["electric", "steel"]},
	{"id":"0463", "gen":4, "variant":1, "name":"Lickilicky", "type":["normal"]},
	{"id":"0464", "gen":4, "variant":1, "name":"Rhyperior", "type":["ground", "rock"]},
	{"id":"0465", "gen":4, "variant":1, "name":"Tangrowth", "type":["grass"]},
	{"id":"0466", "gen":4, "variant":1, "name":"Electivire", "type":["electric"]},
	{"id":"0467", "gen":4, "variant":1, "name":"Magmortar", "type":["fire"]},
	{"id":"0468", "gen":4, "variant":1, "name":"Togekiss", "type":["fairy", "flying"]},
	{"id":"0469", "gen":4, "variant":1, "name":"Yanmega", "type":["bug", "flying"]},
	{"id":"0470", "gen":4, "variant":1, "name":"Leafeon", "type":["grass"]},
	{"id":"0471", "gen":4, "variant":1, "name":"Glaceon", "type":["ice"]},
	{"id":"0472", "gen":4, "variant":1, "name":"Gliscor", "type":["ground", "flying"]},
	{"id":"0473", "gen":4, "variant":1, "name":"Mamoswine", "type":["ice", "ground"]},
	{"id":"0474", "gen":4, "variant":1, "name":"Porygon-Z", "type":["normal"]},
	{"id":"0475", "gen":4, "variant":1, "name":"Gallade", "type":["psychic", "fighting"]},
	{"id":"0475", "gen":6, "variant":2, "name":"Mega-Gallade", "type":["psychic", "fighting"], "special":"megaevo"},
	{"id":"0476", "gen":4, "variant":1, "name":"Probopass", "type":["rock", "steel"]},
	{"id":"0477", "gen":4, "variant":1, "name":"Dusknoir", "type":["ghost"]},
	{"id":"0478", "gen":4, "variant":1, "name":"Froslass", "type":["ice", "ghost"]},
	{"id":"0479", "gen":4, "variant":1, "name":"Rotom", "type":["electric", "ghost"]},
	{"id":"0479", "gen":4, "variant":2, "name":"Rotom Calor", "type":["electric", "fire"]},
	{"id":"0479", "gen":4, "variant":3, "name":"Rotom Lavado", "type":["electric", "water"]},
	{"id":"0479", "gen":4, "variant":4, "name":"Rotom Frío", "type":["electric", "ice"]},
	{"id":"0479", "gen":4, "variant":5, "name":"Rotom Ventilador", "type":["electric", "flying"]},
	{"id":"0479", "gen":4, "variant":6, "name":"Rotom Corte", "type":["electric", "grass"]},
	{"id":"0480", "gen":4, "variant":1, "name":"Uxie", "type":["psychic"], "special":"legendary"},
	{"id":"0481", "gen":4, "variant":1, "name":"Mesprit", "type":["psychic"], "special":"legendary"},
	{"id":"0482", "gen":4, "variant":1, "name":"Azelf", "type":["psychic"], "special":"legendary"},
	{"id":"0483", "gen":4, "variant":1, "name":"Dialga", "type":["steel", "dragon"], "special":"legendary"},
	{"id":"0484", "gen":4, "variant":1, "name":"Palkia", "type":["water", "dragon"], "special":"legendary"},
	{"id":"0485", "gen":4, "variant":1, "name":"Heatran", "type":["fire", "steel"], "special":"legendary"},
	{"id":"0486", "gen":4, "variant":1, "name":"Regigigas", "type":["normal"], "special":"legendary"},
	{"id":"0487", "gen":4, "variant":1, "name":"Giratina Forma Modificada", "type":["ghost", "dragon"], "special":"legendary"},
	{"id":"0487", "gen":4, "variant":2, "name":"Giratina Forma Origen", "type":["ghost", "dragon"], "special":"legendary"},
	{"id":"0488", "gen":4, "variant":1, "name":"Cresselia", "type":["psychic"], "special":"legendary"},
	{"id":"0489", "gen":4, "variant":1, "name":"Phione", "type":["water"], "special":"legendary"},
	{"id":"0490", "gen":4, "variant":1, "name":"Manaphy", "type":["water"], "special":"legendary"},
	{"id":"0491", "gen":4, "variant":1, "name":"Darkrai", "type":["dark"], "special":"legendary"},
	{"id":"0492", "gen":4, "variant":1, "name":"Shaymin", "type":["grass"], "special":"legendary"},
	{"id":"0493", "gen":4, "variant":1, "name":"Arceus", "type":["normal"], "special":"legendary"},

	{"id":"0494", "gen":5, "variant":1, "name":"Victini", "type":["psychic", "fire"], "special":"legendary"},
	{"id":"0495", "gen":5, "variant":1, "name":"Snivy", "type":["grass"], "special":"starter"},
	{"id":"0496", "gen":5, "variant":1, "name":"Servine", "type":["grass"]},
	{"id":"0497", "gen":5, "variant":1, "name":"Serperior", "type":["grass"]},
	{"id":"0498", "gen":5, "variant":1, "name":"Tepig", "type":["fire"], "special":"starter"},
	{"id":"0499", "gen":5, "variant":1, "name":"Pignite", "type":["fire", "fighting"]},
	{"id":"0500", "gen":5, "variant":1, "name":"Emboar", "type":["fire", "fighting"]},
	{"id":"0501", "gen":5, "variant":1, "name":"Oshawott", "type":["water"], "special":"starter"},
	{"id":"0502", "gen":5, "variant":1, "name":"Dewott", "type":["water"]},
	{"id":"0503", "gen":5, "variant":1, "name":"Samurott", "type":["water"]},
	{"id":"0503", "gen":8, "variant":2, "name":"Samurott de Hisui", "type":["water", "dark"], "special":"regional"},
	{"id":"0504", "gen":5, "variant":1, "name":"Patrat", "type":["normal"]},
	{"id":"0505", "gen":5, "variant":1, "name":"Watchog", "type":["normal"]},
	{"id":"0506", "gen":5, "variant":1, "name":"Lillipup", "type":["normal"]},
	{"id":"0507", "gen":5, "variant":1, "name":"Herdier", "type":["normal"]},
	{"id":"0508", "gen":5, "variant":1, "name":"Stoutland", "type":["normal"]},
	{"id":"0509", "gen":5, "variant":1, "name":"Purrloin", "type":["dark"]},
	{"id":"0510", "gen":5, "variant":1, "name":"Liepard", "type":["dark"]},
	{"id":"0511", "gen":5, "variant":1, "name":"Pansage", "type":["grass"]},
	{"id":"0512", "gen":5, "variant":1, "name":"Simisage", "type":["grass"]},
	{"id":"0513", "gen":5, "variant":1, "name":"Pansear", "type":["fire"]},
	{"id":"0514", "gen":5, "variant":1, "name":"Simisear", "type":["fire"]},
	{"id":"0515", "gen":5, "variant":1, "name":"Panpour", "type":["water"]},
	{"id":"0516", "gen":5, "variant":1, "name":"Simipour", "type":["water"]},
	{"id":"0517", "gen":5, "variant":1, "name":"Munna", "type":["psychic"]},
	{"id":"0518", "gen":5, "variant":1, "name":"Musharna", "type":["psychic"]},
	{"id":"0519", "gen":5, "variant":1, "name":"Pidove", "type":["normal", "flying"]},
	{"id":"0520", "gen":5, "variant":1, "name":"Tranquill", "type":["normal", "flying"]},
	{"id":"0521", "gen":5, "variant":1, "name":"Unfezant", "type":["normal", "flying"]},
	{"id":"0522", "gen":5, "variant":1, "name":"Blitzle", "type":["electric"]},
	{"id":"0523", "gen":5, "variant":1, "name":"Zebstrika", "type":["electric"]},
	{"id":"0524", "gen":5, "variant":1, "name":"Roggenrola", "type":["rock"]},
	{"id":"0525", "gen":5, "variant":1, "name":"Boldore", "type":["rock"]},
	{"id":"0526", "gen":5, "variant":1, "name":"Gigalith", "type":["rock"]},
	{"id":"0527", "gen":5, "variant":1, "name":"Woobat", "type":["psychic", "flying"]},
	{"id":"0528", "gen":5, "variant":1, "name":"Swoobat", "type":["psychic", "flying"]},
	{"id":"0529", "gen":5, "variant":1, "name":"Drilbur", "type":["ground"]},
	{"id":"0530", "gen":5, "variant":1, "name":"Excadrill", "type":["ground", "steel"]},
	{"id":"0531", "gen":5, "variant":1, "name":"Audino", "type":["normal"]},
	{"id":"0531", "gen":6, "variant":2, "name":"Mega-Audino", "type":["normal", "fairy"], "special":"megaevo"},
	{"id":"0532", "gen":5, "variant":1, "name":"Timburr", "type":["fighting"]},
	{"id":"0533", "gen":5, "variant":1, "name":"Gurdurr", "type":["fighting"]},
	{"id":"0534", "gen":5, "variant":1, "name":"Conkeldurr", "type":["fighting"]},
	{"id":"0535", "gen":5, "variant":1, "name":"Tympole", "type":["water"]},
	{"id":"0536", "gen":5, "variant":1, "name":"Palpitoad", "type":["water", "ground"]},
	{"id":"0537", "gen":5, "variant":1, "name":"Seismitoad", "type":["water", "ground"]},
	{"id":"0538", "gen":5, "variant":1, "name":"Throh", "type":["fighting"]},
	{"id":"0539", "gen":5, "variant":1, "name":"Sawk", "type":["fighting"]},
	{"id":"0540", "gen":5, "variant":1, "name":"Sewaddle", "type":["bug", "grass"]},
	{"id":"0541", "gen":5, "variant":1, "name":"Swadloon", "type":["bug", "grass"]},
	{"id":"0542", "gen":5, "variant":1, "name":"Leavanny", "type":["bug", "grass"]},
	{"id":"0543", "gen":5, "variant":1, "name":"Venipede", "type":["bug", "poison"]},
	{"id":"0544", "gen":5, "variant":1, "name":"Whirlipede", "type":["bug", "poison"]},
	{"id":"0545", "gen":5, "variant":1, "name":"Scolipede", "type":["bug", "poison"]},
	{"id":"0546", "gen":5, "variant":1, "name":"Cottonee", "type":["grass", "fairy"]},
	{"id":"0547", "gen":5, "variant":1, "name":"Whimsicott", "type":["grass", "fairy"]},
	{"id":"0548", "gen":5, "variant":1, "name":"Petilil", "type":["grass"]},
	{"id":"0549", "gen":5, "variant":1, "name":"Lilligant", "type":["grass"]},
	{"id":"0549", "gen":8, "variant":2, "name":"Lilligant de Hisui", "type":["grass", "fighting"], "special":"regional"},
	{"id":"0550", "gen":5, "variant":1, "name":"Basculin", "type":["water"]},
	{"id":"0551", "gen":5, "variant":1, "name":"Sandile", "type":["ground", "dark"]},
	{"id":"0552", "gen":5, "variant":1, "name":"Krokorok", "type":["ground", "dark"]},
	{"id":"0553", "gen":5, "variant":1, "name":"Krookodile", "type":["ground", "dark"]},
	{"id":"0554", "gen":5, "variant":1, "name":"Darumaka", "type":["fire"]},
	{"id":"0554", "gen":8, "variant":2, "name":"Darumaka de Galar", "type":["ice"], "special":"regional"},
	{"id":"0555", "gen":5, "variant":1, "name":"Darmanitan", "type":["fire"]},
	{"id":"0555", "gen":8, "variant":2, "name":"Darmanitan de Galar", "type":["ice"], "special":"regional"},
	{"id":"0556", "gen":5, "variant":1, "name":"Maractus", "type":["grass"]},
	{"id":"0557", "gen":5, "variant":1, "name":"Dwebble", "type":["bug", "rock"]},
	{"id":"0558", "gen":5, "variant":1, "name":"Crustle", "type":["bug", "rock"]},
	{"id":"0559", "gen":5, "variant":1, "name":"Scraggy", "type":["dark", "fighting"]},
	{"id":"0560", "gen":5, "variant":1, "name":"Scrafty", "type":["dark", "fighting"]},
	{"id":"0561", "gen":5, "variant":1, "name":"Sigilyph", "type":["psychic", "flying"]},
	{"id":"0562", "gen":5, "variant":1, "name":"Yamask", "type":["ghost"]},
	{"id":"0562", "gen":8, "variant":2, "name":"Yamask de Galar", "type":["ground", "ghost"], "special":"regional"},
	{"id":"0563", "gen":5, "variant":1, "name":"Cofagrigus", "type":["ghost"]},
	{"id":"0564", "gen":5, "variant":1, "name":"Tirtouga", "type":["water", "rock"]},
	{"id":"0565", "gen":5, "variant":1, "name":"Carracosta", "type":["water", "rock"]},
	{"id":"0566", "gen":5, "variant":1, "name":"Archen", "type":["rock", "flying"]},
	{"id":"0567", "gen":5, "variant":1, "name":"Archeops", "type":["rock", "flying"]},
	{"id":"0568", "gen":5, "variant":1, "name":"Trubbish", "type":["poison"]},
	{"id":"0569", "gen":5, "variant":1, "name":"Garbodor", "type":["poison"]},
	{"id":"0570", "gen":5, "variant":1, "name":"Zorua", "type":["dark"]},
	{"id":"0570", "gen":8, "variant":2, "name":"Zorua de Hisui", "type":["normal", "ghost"], "special":"regional"},
	{"id":"0571", "gen":5, "variant":1, "name":"Zoroark", "type":["dark"]},
	{"id":"0571", "gen":8, "variant":2, "name":"Zoroark de Hisui", "type":["normal", "ghost"], "special":"regional"},
	{"id":"0572", "gen":5, "variant":1, "name":"Minccino", "type":["normal"]},
	{"id":"0573", "gen":5, "variant":1, "name":"Cinccino", "type":["normal"]},
	{"id":"0574", "gen":5, "variant":1, "name":"Gothita", "type":["psychic"]},
	{"id":"0575", "gen":5, "variant":1, "name":"Gothorita", "type":["psychic"]},
	{"id":"0576", "gen":5, "variant":1, "name":"Gothitelle", "type":["psychic"]},
	{"id":"0577", "gen":5, "variant":1, "name":"Solosis", "type":["psychic"]},
	{"id":"0578", "gen":5, "variant":1, "name":"Duosion", "type":["psychic"]},
	{"id":"0579", "gen":5, "variant":1, "name":"Reuniclus", "type":["psychic"]},
	{"id":"0580", "gen":5, "variant":1, "name":"Ducklett", "type":["water", "flying"]},
	{"id":"0581", "gen":5, "variant":1, "name":"Swanna", "type":["water", "flying"]},
	{"id":"0582", "gen":5, "variant":1, "name":"Vanillite", "type":["ice"]},
	{"id":"0583", "gen":5, "variant":1, "name":"Vanillish", "type":["ice"]},
	{"id":"0584", "gen":5, "variant":1, "name":"Vanilluxe", "type":["ice"]},
	{"id":"0585", "gen":5, "variant":1, "name":"Deerling", "type":["normal", "grass"]},
	{"id":"0586", "gen":5, "variant":1, "name":"Sawsbuck (Primavera)", "type":["normal", "grass"]},
	{"id":"0586", "gen":5, "variant":2, "name":"Sawsbuck (Verano)", "type":["normal", "grass"]},
	{"id":"0586", "gen":5, "variant":3, "name":"Sawsbuck (Otoño)", "type":["normal", "grass"]},
	{"id":"0586", "gen":5, "variant":4, "name":"Sawsbuck (Invierno)", "type":["normal", "grass"]},
	{"id":"0587", "gen":5, "variant":1, "name":"Emolga", "type":["electric", "flying"]},
	{"id":"0588", "gen":5, "variant":1, "name":"Karrablast", "type":["bug"]},
	{"id":"0589", "gen":5, "variant":1, "name":"Escavalier", "type":["bug", "steel"]},
	{"id":"0590", "gen":5, "variant":1, "name":"Foongus", "type":["grass", "poison"]},
	{"id":"0591", "gen":5, "variant":1, "name":"Amoonguss", "type":["grass", "poison"]},
	{"id":"0592", "gen":5, "variant":1, "name":"Frillish (Macho)", "type":["water", "ghost"]},
	{"id":"0592", "gen":5, "variant":2, "name":"Frillish (Hembra)", "type":["water", "ghost"]},
	{"id":"0593", "gen":5, "variant":1, "name":"Jellicent (Macho)", "type":["water", "ghost"]},
	{"id":"0593", "gen":5, "variant":2, "name":"Jellicent (Hembra)", "type":["water", "ghost"]},
	{"id":"0594", "gen":5, "variant":1, "name":"Alomomola", "type":["water"]},
	{"id":"0595", "gen":5, "variant":1, "name":"Joltik", "type":["bug", "electric"]},
	{"id":"0596", "gen":5, "variant":1, "name":"Galvantula", "type":["bug", "electric"]},
	{"id":"0597", "gen":5, "variant":1, "name":"Ferroseed", "type":["grass", "steel"]},
	{"id":"0598", "gen":5, "variant":1, "name":"Ferrothorn", "type":["grass", "steel"]},
	{"id":"0599", "gen":5, "variant":1, "name":"Klink", "type":["steel"]},
	{"id":"0600", "gen":5, "variant":1, "name":"Klang", "type":["steel"]},
	{"id":"0601", "gen":5, "variant":1, "name":"Klinklang", "type":["steel"]},
	{"id":"0602", "gen":5, "variant":1, "name":"Tynamo", "type":["electric"]},
	{"id":"0603", "gen":5, "variant":1, "name":"Eelektrik", "type":["electric"]},
	{"id":"0604", "gen":5, "variant":1, "name":"Eelektross", "type":["electric"]},
	{"id":"0605", "gen":5, "variant":1, "name":"Elgyem", "type":["psychic"]},
	{"id":"0606", "gen":5, "variant":1, "name":"Beheeyem", "type":["psychic"]},
	{"id":"0607", "gen":5, "variant":1, "name":"Litwick", "type":["ghost", "fire"]},
	{"id":"0608", "gen":5, "variant":1, "name":"Lampent", "type":["ghost", "fire"]},
	{"id":"0609", "gen":5, "variant":1, "name":"Chandelure", "type":["ghost", "fire"]},
	{"id":"0610", "gen":5, "variant":1, "name":"Axew", "type":["dragon"]},
	{"id":"0611", "gen":5, "variant":1, "name":"Fraxure", "type":["dragon"]},
	{"id":"0612", "gen":5, "variant":1, "name":"Haxorus", "type":["dragon"]},
	{"id":"0613", "gen":5, "variant":1, "name":"Cubchoo", "type":["ice"]},
	{"id":"0614", "gen":5, "variant":1, "name":"Beartic", "type":["ice"]},
	{"id":"0615", "gen":5, "variant":1, "name":"Cryogonal", "type":["ice"]},
	{"id":"0616", "gen":5, "variant":1, "name":"Shelmet", "type":["bug"]},
	{"id":"0617", "gen":5, "variant":1, "name":"Accelgor", "type":["bug"]},
	{"id":"0618", "gen":5, "variant":1, "name":"Stunfisk", "type":["ground", "electric"]},
	{"id":"0618", "gen":8, "variant":2, "name":"Stunfisk de Galar", "type":["ground", "steel"], "special":"regional"},
	{"id":"0619", "gen":5, "variant":1, "name":"Mienfoo", "type":["fighting"]},
	{"id":"0620", "gen":5, "variant":1, "name":"Mienshao", "type":["fighting"]},
	{"id":"0621", "gen":5, "variant":1, "name":"Druddigon", "type":["dragon"]},
	{"id":"0622", "gen":5, "variant":1, "name":"Golett", "type":["ground", "ghost"]},
	{"id":"0623", "gen":5, "variant":1, "name":"Golurk", "type":["ground", "ghost"]},
	{"id":"0624", "gen":5, "variant":1, "name":"Pawniard", "type":["dark", "steel"]},
	{"id":"0625", "gen":5, "variant":1, "name":"Bisharp", "type":["dark", "steel"]},
	{"id":"0626", "gen":5, "variant":1, "name":"Bouffalant", "type":["normal"]},
	{"id":"0627", "gen":5, "variant":1, "name":"Rufflet", "type":["normal", "flying"]},
	{"id":"0628", "gen":5, "variant":1, "name":"Braviary", "type":["normal", "flying"]},
	{"id":"0628", "gen":8, "variant":2, "name":"Braviary de Hisui", "type":["psychic", "flying"], "special":"regional"},
	{"id":"0629", "gen":5, "variant":1, "name":"Vullaby", "type":["dark", "flying"]},
	{"id":"0630", "gen":5, "variant":1, "name":"Mandibuzz", "type":["dark", "flying"]},
	{"id":"0631", "gen":5, "variant":1, "name":"Heatmor", "type":["fire"]},
	{"id":"0632", "gen":5, "variant":1, "name":"Durant", "type":["bug", "steel"]},
	{"id":"0633", "gen":5, "variant":1, "name":"Deino", "type":["dark", "dragon"]},
	{"id":"0634", "gen":5, "variant":1, "name":"Zweilous", "type":["dark", "dragon"]},
	{"id":"0635", "gen":5, "variant":1, "name":"Hydreigon", "type":["dark", "dragon"]},
	{"id":"0636", "gen":5, "variant":1, "name":"Larvesta", "type":["bug", "fire"]},
	{"id":"0637", "gen":5, "variant":1, "name":"Volcarona", "type":["bug", "fire"]},
	{"id":"0638", "gen":5, "variant":1, "name":"Cobalion", "type":["steel", "fighting"], "special":"legendary"},
	{"id":"0639", "gen":5, "variant":1, "name":"Terrakion", "type":["rock", "fighting"], "special":"legendary"},
	{"id":"0640", "gen":5, "variant":1, "name":"Virizion", "type":["grass", "fighting"], "special":"legendary"},
	{"id":"0641", "gen":5, "variant":1, "name":"Tornadus (Avatar)", "type":["flying"], "special":"legendary"},
	{"id":"0641", "gen":5, "variant":2, "name":"Tornadus (Totem)", "type":["flying"], "special":"legendary"},
	{"id":"0642", "gen":5, "variant":1, "name":"Thundurus (Avatar)", "type":["electric", "flying"], "special":"legendary"},
	{"id":"0642", "gen":5, "variant":2, "name":"Thundurus (Totem)", "type":["electric", "flying"], "special":"legendary"},
	{"id":"0643", "gen":5, "variant":1, "name":"Reshiram", "type":["dragon", "fire"], "special":"legendary"},
	{"id":"0644", "gen":5, "variant":1, "name":"Zekrom", "type":["dragon", "electric"], "special":"legendary"},
	{"id":"0645", "gen":5, "variant":1, "name":"Landorus (Avatar)", "type":["ground", "flying"], "special":"legendary"},
	{"id":"0645", "gen":5, "variant":2, "name":"Landorus (Totem)", "type":["ground", "flying"], "special":"legendary"},
	{"id":"0646", "gen":5, "variant":1, "name":"Kyurem", "type":["dragon", "ice"], "special":"legendary"},
	{"id":"0646", "gen":5, "variant":2, "name":"Kyurem Blanco", "type":["dragon", "ice"], "special":"legendary"},
	{"id":"0646", "gen":5, "variant":3, "name":"Kyurem Negro", "type":["dragon", "ice"], "special":"legendary"},
	{"id":"0647", "gen":5, "variant":1, "name":"Keldeo", "type":["water", "fighting"], "special":"legendary"},
	{"id":"0647", "gen":5, "variant":2, "name":"Keldeo (Brío)", "type":["water", "fighting"], "special":"legendary"},
	{"id":"0648", "gen":5, "variant":1, "name":"Meloetta (Lírico)", "type":["normal", "psychic"], "special":"legendary"},
	{"id":"0648", "gen":5, "variant":2, "name":"Meloetta (Danza)", "type":["normal", "fighting"], "special":"legendary"},
	{"id":"0649", "gen":5, "variant":1, "name":"Genesect", "type":["bug", "steel"], "special":"legendary"},

	{"id":"0650", "gen":6, "variant":1, "name":"Chespin", "type":["grass"], "special":"starter"},
	{"id":"0651", "gen":6, "variant":1, "name":"Quilladin", "type":["grass"]},
	{"id":"0652", "gen":6, "variant":1, "name":"Chesnaught", "type":["grass", "fighting"]},
	{"id":"0653", "gen":6, "variant":1, "name":"Fennekin", "type":["fire"], "special":"starter"},
	{"id":"0654", "gen":6, "variant":1, "name":"Braixen", "type":["fire"]},
	{"id":"0655", "gen":6, "variant":1, "name":"Delphox", "type":["fire", "psychic"]},
	{"id":"0656", "gen":6, "variant":1, "name":"Froakie", "type":["water"], "special":"starter"},
	{"id":"0657", "gen":6, "variant":1, "name":"Frogadier", "type":["water"]},
	{"id":"0658", "gen":6, "variant":1, "name":"Greninja", "type":["water", "dark"]},
	{"id":"0659", "gen":6, "variant":1, "name":"Bunnelby", "type":["normal"]},
	{"id":"0660", "gen":6, "variant":1, "name":"Diggersby", "type":["normal", "ground"]},
	{"id":"0661", "gen":6, "variant":1, "name":"Fletchling", "type":["normal", "flying"]},
	{"id":"0662", "gen":6, "variant":1, "name":"Fletchinder", "type":["fire", "flying"]},
	{"id":"0663", "gen":6, "variant":1, "name":"Talonflame", "type":["fire", "flying"]},
	{"id":"0664", "gen":6, "variant":1, "name":"Scatterbug", "type":["bug"]},
	{"id":"0665", "gen":6, "variant":1, "name":"Spewpa", "type":["bug"]},
	{"id":"0666", "gen":6, "variant":1, "name":"Vivillon", "type":["bug", "flying"]},
	{"id":"0667", "gen":6, "variant":1, "name":"Litleo", "type":["fire", "normal"]},
	{"id":"0668", "gen":6, "variant":1, "name":"Pyroar", "type":["fire", "normal"]},
	{"id":"0669", "gen":6, "variant":1, "name":"Flabébé", "type":["fairy"]},
	{"id":"0670", "gen":6, "variant":1, "name":"Floette", "type":["fairy"]},
	{"id":"0671", "gen":6, "variant":1, "name":"Florges", "type":["fairy"]},
	{"id":"0672", "gen":6, "variant":1, "name":"Skiddo", "type":["grass"]},
	{"id":"0673", "gen":6, "variant":1, "name":"Gogoat", "type":["grass"]},
	{"id":"0674", "gen":6, "variant":1, "name":"Pancham", "type":["fighting"]},
	{"id":"0675", "gen":6, "variant":1, "name":"Pangoro", "type":["fighting", "dark"]},
	{"id":"0676", "gen":6, "variant":1, "name":"Furfrou", "type":["normal"]},
	{"id":"0677", "gen":6, "variant":1, "name":"Espurr", "type":["psychic"]},
	{"id":"0678", "gen":6, "variant":1, "name":"Meowstic", "type":["psychic"]},
	{"id":"0679", "gen":6, "variant":1, "name":"Honedge", "type":["steel", "ghost"]},
	{"id":"0680", "gen":6, "variant":1, "name":"Doublade", "type":["steel", "ghost"]},
	{"id":"0681", "gen":6, "variant":1, "name":"Aegislash", "type":["steel", "ghost"]},
	{"id":"0682", "gen":6, "variant":1, "name":"Spritzee", "type":["fairy"]},
	{"id":"0683", "gen":6, "variant":1, "name":"Aromatisse", "type":["fairy"]},
	{"id":"0684", "gen":6, "variant":1, "name":"Swirlix", "type":["fairy"]},
	{"id":"0685", "gen":6, "variant":1, "name":"Slurpuff", "type":["fairy"]},
	{"id":"0686", "gen":6, "variant":1, "name":"Inkay", "type":["dark", "psychic"]},
	{"id":"0687", "gen":6, "variant":1, "name":"Malamar", "type":["dark", "psychic"]},
	{"id":"0688", "gen":6, "variant":1, "name":"Binacle", "type":["rock", "water"]},
	{"id":"0689", "gen":6, "variant":1, "name":"Barbaracle", "type":["rock", "water"]},
	{"id":"0690", "gen":6, "variant":1, "name":"Skrelp", "type":["poison", "water"]},
	{"id":"0691", "gen":6, "variant":1, "name":"Dragalge", "type":["poison", "dragon"]},
	{"id":"0692", "gen":6, "variant":1, "name":"Clauncher", "type":["water"]},
	{"id":"0693", "gen":6, "variant":1, "name":"Clawitzer", "type":["water"]},
	{"id":"0694", "gen":6, "variant":1, "name":"Helioptile", "type":["electric", "normal"]},
	{"id":"0695", "gen":6, "variant":1, "name":"Heliolisk", "type":["electric", "normal"]},
	{"id":"0696", "gen":6, "variant":1, "name":"Tyrunt", "type":["rock", "dragon"]},
	{"id":"0697", "gen":6, "variant":1, "name":"Tyrantrum", "type":["rock", "dragon"]},
	{"id":"0698", "gen":6, "variant":1, "name":"Amaura", "type":["rock", "ice"]},
	{"id":"0699", "gen":6, "variant":1, "name":"Aurorus", "type":["rock", "ice"]},
	{"id":"0700", "gen":6, "variant":1, "name":"Sylveon", "type":["fairy"]},
	{"id":"0701", "gen":6, "variant":1, "name":"Hawlucha", "type":["fighting", "flying"]},
	{"id":"0702", "gen":6, "variant":1, "name":"Dedenne", "type":["electric", "fairy"]},
	{"id":"0703", "gen":6, "variant":1, "name":"Carbink", "type":["rock", "fairy"]},
	{"id":"0704", "gen":6, "variant":1, "name":"Goomy", "type":["dragon"]},
	{"id":"0705", "gen":6, "variant":1, "name":"Sliggoo", "type":["dragon"]},
	{"id":"0705", "gen":8, "variant":2, "name":"Sliggoo de Hisui", "type":["steel", "dragon"], "special":"regional"},
	{"id":"0706", "gen":6, "variant":1, "name":"Goodra", "type":["dragon"]},
	{"id":"0706", "gen":8, "variant":2, "name":"Goodra de Hisui", "type":["steel", "dragon"], "special":"regional"},
	{"id":"0707", "gen":6, "variant":1, "name":"Klefki", "type":["steel", "fairy"]},
	{"id":"0708", "gen":6, "variant":1, "name":"Phantump", "type":["ghost", "grass"]},
	{"id":"0709", "gen":6, "variant":1, "name":"Trevenant", "type":["ghost", "grass"]},
	{"id":"0710", "gen":6, "variant":1, "name":"Pumpkaboo", "type":["ghost", "grass"]},
	{"id":"0711", "gen":6, "variant":1, "name":"Gourgeist", "type":["ghost", "grass"]},
	{"id":"0712", "gen":6, "variant":1, "name":"Bergmite", "type":["ice"]},
	{"id":"0713", "gen":6, "variant":1, "name":"Avalugg", "type":["ice"]},
	{"id":"0713", "gen":8, "variant":2, "name":"Avalugg de Hisui", "type":["ice", "rock"], "special":"regional"},
	{"id":"0714", "gen":6, "variant":1, "name":"Noibat", "type":["flying", "dragon"]},
	{"id":"0715", "gen":6, "variant":1, "name":"Noivern", "type":["flying", "dragon"]},
	{"id":"0716", "gen":6, "variant":1, "name":"Xerneas", "type":["fairy"], "special":"legendary"},
	{"id":"0717", "gen":6, "variant":1, "name":"Yveltal", "type":["dark", "flying"], "special":"legendary"},
	{"id":"0718", "gen":6, "variant":1, "name":"Zygarde 50%", "type":["dragon", "ground"], "special":"legendary"},
	{"id":"0718", "gen":6, "variant":2, "name":"Zygarde 10%", "type":["dragon", "ground"], "special":"legendary"},
	{"id":"0718", "gen":6, "variant":3, "name":"Zygarde 100%", "type":["dragon", "ground"], "special":"legendary"},
	{"id":"0719", "gen":6, "variant":1, "name":"Diancie", "type":["rock", "fairy"], "special":"legendary"},
	{"id":"0719", "gen":6, "variant":2, "name":"Mega-Diancie", "type":["rock", "fairy"], "special":"megaevo"},
	{"id":"0720", "gen":6, "variant":1, "name":"Hoopa Contenido", "type":["psychic", "ghost"], "special":"legendary"},
	{"id":"0720", "gen":6, "variant":2, "name":"Hoopa Desatado", "type":["psychic", "dark"], "special":"legendary"},
	{"id":"0721", "gen":6, "variant":1, "name":"Volcanion", "type":["fire", "water"], "special":"legendary"},

	{"id":"0722", "gen":7, "variant":1, "name":"Rowlet", "type":["grass", "flying"], "special":"starter"},
	{"id":"0723", "gen":7, "variant":1, "name":"Dartrix", "type":["grass", "flying"]},
	{"id":"0724", "gen":7, "variant":1, "name":"Decidueye", "type":["grass", "ghost"]},
	{"id":"0724", "gen":8, "variant":2, "name":"Decidueye de Hisui", "type":["grass", "fighting"], "special":"regional"},
	{"id":"0725", "gen":7, "variant":1, "name":"Litten", "type":["fire"], "special":"starter"},
	{"id":"0726", "gen":7, "variant":1, "name":"Torracat", "type":["fire"]},
	{"id":"0727", "gen":7, "variant":1, "name":"Incineroar", "type":["fire", "dark"]},
	{"id":"0728", "gen":7, "variant":1, "name":"Popplio", "type":["water"], "special":"starter"},
	{"id":"0729", "gen":7, "variant":1, "name":"Brionne", "type":["water"]},
	{"id":"0730", "gen":7, "variant":1, "name":"Primarina", "type":["water", "fairy"]},
	{"id":"0731", "gen":7, "variant":1, "name":"Pikipek", "type":["normal", "flying"]},
	{"id":"0732", "gen":7, "variant":1, "name":"Trumbeak", "type":["normal", "flying"]},
	{"id":"0733", "gen":7, "variant":1, "name":"Toucannon", "type":["normal", "flying"]},
	{"id":"0734", "gen":7, "variant":1, "name":"Yungoos", "type":["normal"]},
	{"id":"0735", "gen":7, "variant":1, "name":"Gumshoos", "type":["normal"]},
	{"id":"0736", "gen":7, "variant":1, "name":"Grubbin", "type":["bug"]},
	{"id":"0737", "gen":7, "variant":1, "name":"Charjabug", "type":["bug", "electric"]},
	{"id":"0738", "gen":7, "variant":1, "name":"Vikavolt", "type":["bug", "electric"]},
	{"id":"0739", "gen":7, "variant":1, "name":"Crabrawler", "type":["fighting"]},
	{"id":"0740", "gen":7, "variant":1, "name":"Crabominable", "type":["fighting", "ice"]},
	{"id":"0741", "gen":7, "variant":1, "name":"Oricorio", "type":["fire", "flying"]},
	{"id":"0742", "gen":7, "variant":1, "name":"Cutiefly", "type":["bug", "fairy"]},
	{"id":"0743", "gen":7, "variant":1, "name":"Ribombee", "type":["bug", "fairy"]},
	{"id":"0744", "gen":7, "variant":1, "name":"Rockruff", "type":["rock"]},
	{"id":"0745", "gen":7, "variant":1, "name":"Lycanroc", "type":["rock"]},
	{"id":"0746", "gen":7, "variant":1, "name":"Wishiwashi (Individual)", "type":["water"]},
	{"id":"0746", "gen":7, "variant":2, "name":"Wishiwashi (Banco)", "type":["water"]},
	{"id":"0747", "gen":7, "variant":1, "name":"Mareanie", "type":["poison", "water"]},
	{"id":"0748", "gen":7, "variant":1, "name":"Toxapex", "type":["poison", "water"]},
	{"id":"0749", "gen":7, "variant":1, "name":"Mudbray", "type":["ground"]},
	{"id":"0750", "gen":7, "variant":1, "name":"Mudsdale", "type":["ground"]},
	{"id":"0751", "gen":7, "variant":1, "name":"Dewpider", "type":["water", "bug"]},
	{"id":"0752", "gen":7, "variant":1, "name":"Araquanid", "type":["water", "bug"]},
	{"id":"0753", "gen":7, "variant":1, "name":"Fomantis", "type":["grass"]},
	{"id":"0754", "gen":7, "variant":1, "name":"Lurantis", "type":["grass"]},
	{"id":"0755", "gen":7, "variant":1, "name":"Morelull", "type":["grass", "fairy"]},
	{"id":"0756", "gen":7, "variant":1, "name":"Shiinotic", "type":["grass", "fairy"]},
	{"id":"0757", "gen":7, "variant":1, "name":"Salandit", "type":["poison", "fire"]},
	{"id":"0758", "gen":7, "variant":1, "name":"Salazzle", "type":["poison", "fire"]},
	{"id":"0759", "gen":7, "variant":1, "name":"Stufful", "type":["normal", "fighting"]},
	{"id":"0760", "gen":7, "variant":1, "name":"Bewear", "type":["normal", "fighting"]},
	{"id":"0761", "gen":7, "variant":1, "name":"Bounsweet", "type":["grass"]},
	{"id":"0762", "gen":7, "variant":1, "name":"Steenee", "type":["grass"]},
	{"id":"0763", "gen":7, "variant":1, "name":"Tsareena", "type":["grass"]},
	{"id":"0764", "gen":7, "variant":1, "name":"Comfey", "type":["fairy"]},
	{"id":"0765", "gen":7, "variant":1, "name":"Oranguru", "type":["normal", "psychic"]},
	{"id":"0766", "gen":7, "variant":1, "name":"Passimian", "type":["fighting"]},
	{"id":"0767", "gen":7, "variant":1, "name":"Wimpod", "type":["bug", "water"]},
	{"id":"0768", "gen":7, "variant":1, "name":"Golisopod", "type":["bug", "water"]},
	{"id":"0769", "gen":7, "variant":1, "name":"Sandygast", "type":["ghost", "ground"]},
	{"id":"0770", "gen":7, "variant":1, "name":"Palossand", "type":["ghost", "ground"]},
	{"id":"0771", "gen":7, "variant":1, "name":"Pyukumuku", "type":["water"]},
	{"id":"0772", "gen":7, "variant":1, "name":"Código Cero", "type":["normal"], "special":"legendary"},
	{"id":"0773", "gen":7, "variant":1, "name":"Silvally", "type":["normal"], "special":"legendary"},
	{"id":"0774", "gen":7, "variant":1, "name":"Minior (Meteorito)", "type":["rock", "flying"]},
	{"id":"0774", "gen":7, "variant":2, "name":"Minior (Núcleo Rojo)", "type":["rock", "flying"]},
	{"id":"0775", "gen":7, "variant":1, "name":"Komala", "type":["normal"]},
	{"id":"0776", "gen":7, "variant":1, "name":"Turtonator", "type":["fire", "dragon"]},
	{"id":"0777", "gen":7, "variant":1, "name":"Togedemaru", "type":["electric", "steel"]},
	{"id":"0778", "gen":7, "variant":1, "name":"Mimikyu", "type":["ghost", "fairy"]},
	{"id":"0779", "gen":7, "variant":1, "name":"Bruxish", "type":["water", "psychic"]},
	{"id":"0780", "gen":7, "variant":1, "name":"Drampa", "type":["normal", "dragon"]},
	{"id":"0781", "gen":7, "variant":1, "name":"Dhelmise", "type":["ghost", "grass"]},
	{"id":"0782", "gen":7, "variant":1, "name":"Jangmo-o", "type":["dragon"]},
	{"id":"0783", "gen":7, "variant":1, "name":"Hakamo-o", "type":["dragon", "fighting"]},
	{"id":"0784", "gen":7, "variant":1, "name":"Kommo-o", "type":["dragon", "fighting"]},
	{"id":"0785", "gen":7, "variant":1, "name":"Tapu Koko", "type":["electric", "fairy"], "special":"legendary"},
	{"id":"0786", "gen":7, "variant":1, "name":"Tapu Lele", "type":["psychic", "fairy"], "special":"legendary"},
	{"id":"0787", "gen":7, "variant":1, "name":"Tapu Bulu", "type":["grass", "fairy"], "special":"legendary"},
	{"id":"0788", "gen":7, "variant":1, "name":"Tapu Fini", "type":["water", "fairy"], "special":"legendary"},
	{"id":"0789", "gen":7, "variant":1, "name":"Cosmog", "type":["psychic"], "special":"legendary"},
	{"id":"0790", "gen":7, "variant":1, "name":"Cosmoem", "type":["psychic"], "special":"legendary"},
	{"id":"0791", "gen":7, "variant":1, "name":"Solgaleo", "type":["psychic", "steel"], "special":"legendary"},
	{"id":"0792", "gen":7, "variant":1, "name":"Lunala", "type":["psychic", "ghost"], "special":"legendary"},
	{"id":"0793", "gen":7, "variant":1, "name":"Nihilego", "type":["rock", "poison"], "special":"ultrabeast"},
	{"id":"0794", "gen":7, "variant":1, "name":"Buzzwole", "type":["bug", "fighting"], "special":"ultrabeast"},
	{"id":"0795", "gen":7, "variant":1, "name":"Pheromosa", "type":["bug", "fighting"], "special":"ultrabeast"},
	{"id":"0796", "gen":7, "variant":1, "name":"Xurkitree", "type":["electric"], "special":"ultrabeast"},
	{"id":"0797", "gen":7, "variant":1, "name":"Celesteela", "type":["steel", "flying"], "special":"ultrabeast"},
	{"id":"0798", "gen":7, "variant":1, "name":"Kartana", "type":["grass", "steel"], "special":"ultrabeast"},
	{"id":"0799", "gen":7, "variant":1, "name":"Guzzlord", "type":["dark", "dragon"], "special":"ultrabeast"},
	{"id":"0800", "gen":7, "variant":1, "name":"Necrozma", "type":["psychic"], "special":"legendary"},
	{"id":"0800", "gen":7, "variant":2, "name":"Necrozma melena crepuscular", "type":["psychic", "steel"], "special":"legendary"},
	{"id":"0800", "gen":7, "variant":3, "name":"Necrozma alas del alba", "type":["psychic", "ghost"], "special":"legendary"},
	{"id":"0800", "gen":7, "variant":4, "name":"Ultra-Necrozma", "type":["psychic", "dragon"], "special":"legendary"},
	{"id":"0801", "gen":7, "variant":1, "name":"Magearna", "type":["steel", "fairy"], "special":"legendary"},
	{"id":"0802", "gen":7, "variant":1, "name":"Marshadow", "type":["fighting", "ghost"], "special":"legendary"},
	{"id":"0803", "gen":7, "variant":1, "name":"Poipole", "type":["poison"], "special":"ultrabeast"},
	{"id":"0804", "gen":7, "variant":1, "name":"Naganadel", "type":["poison", "dragon"], "special":"ultrabeast"},
	{"id":"0805", "gen":7, "variant":1, "name":"Stakataka", "type":["rock", "steel"], "special":"ultrabeast"},
	{"id":"0806", "gen":7, "variant":1, "name":"Blacephalon", "type":["fire", "ghost"], "special":"ultrabeast"},
	{"id":"0807", "gen":7, "variant":1, "name":"Zeraora", "type":["electric"], "special":"legendary"},
	{"id":"0808", "gen":7, "variant":1, "name":"Meltan", "type":["steel"], "special":"legendary"},
	{"id":"0809", "gen":7, "variant":1, "name":"Melmetal", "type":["steel"], "special":"legendary"},

	{"id":"0810", "gen":8, "variant":1, "name":"Grookey", "type":["grass"], "special":"starter"},
	{"id":"0811", "gen":8, "variant":1, "name":"Thwackey", "type":["grass"]},
	{"id":"0812", "gen":8, "variant":1, "name":"Rillaboom", "type":["grass"]},
	{"id":"0813", "gen":8, "variant":1, "name":"Scorbunny", "type":["fire"], "special":"starter"},
	{"id":"0814", "gen":8, "variant":1, "name":"Raboot", "type":["fire"]},
	{"id":"0815", "gen":8, "variant":1, "name":"Cinderace", "type":["fire"]},
	{"id":"0816", "gen":8, "variant":1, "name":"Sobble", "type":["water"], "special":"starter"},
	{"id":"0817", "gen":8, "variant":1, "name":"Drizzile", "type":["water"]},
	{"id":"0818", "gen":8, "variant":1, "name":"Inteleon", "type":["water"]},
	{"id":"0819", "gen":8, "variant":1, "name":"Skwovet", "type":["normal"]},
	{"id":"0820", "gen":8, "variant":1, "name":"Greedent", "type":["normal"]},
	{"id":"0821", "gen":8, "variant":1, "name":"Rookidee", "type":["flying"]},
	{"id":"0822", "gen":8, "variant":1, "name":"Corvisquire", "type":["flying"]},
	{"id":"0823", "gen":8, "variant":1, "name":"Corviknight", "type":["flying", "steel"]},
	{"id":"0824", "gen":8, "variant":1, "name":"Blipbug", "type":["bug"]},
	{"id":"0825", "gen":8, "variant":1, "name":"Dottler", "type":["bug", "psychic"]},
	{"id":"0826", "gen":8, "variant":1, "name":"Orbeetle", "type":["bug", "psychic"]},
	{"id":"0827", "gen":8, "variant":1, "name":"Nickit", "type":["dark"]},
	{"id":"0828", "gen":8, "variant":1, "name":"Thievul", "type":["dark"]},
	{"id":"0829", "gen":8, "variant":1, "name":"Gossifleur", "type":["grass"]},
	{"id":"0830", "gen":8, "variant":1, "name":"Eldegoss", "type":["grass"]},
	{"id":"0831", "gen":8, "variant":1, "name":"Wooloo", "type":["normal"]},
	{"id":"0832", "gen":8, "variant":1, "name":"Dubwool", "type":["normal"]},
	{"id":"0833", "gen":8, "variant":1, "name":"Chewtle", "type":["water"]},
	{"id":"0834", "gen":8, "variant":1, "name":"Drednaw", "type":["water", "rock"]},
	{"id":"0835", "gen":8, "variant":1, "name":"Yamper", "type":["electric"]},
	{"id":"0836", "gen":8, "variant":1, "name":"Boltund", "type":["electric"]},
	{"id":"0837", "gen":8, "variant":1, "name":"Rolycoly", "type":["rock"]},
	{"id":"0838", "gen":8, "variant":1, "name":"Carkol", "type":["rock", "fire"]},
	{"id":"0839", "gen":8, "variant":1, "name":"Coalossal", "type":["rock", "fire"]},
	{"id":"0840", "gen":8, "variant":1, "name":"Applin", "type":["grass", "dragon"]},
	{"id":"0841", "gen":8, "variant":1, "name":"Flapple", "type":["grass", "dragon"]},
	{"id":"0842", "gen":8, "variant":1, "name":"Appletun", "type":["grass", "dragon"]},
	{"id":"0843", "gen":8, "variant":1, "name":"Silicobra", "type":["ground"]},
	{"id":"0844", "gen":8, "variant":1, "name":"Sandaconda", "type":["ground"]},
	{"id":"0845", "gen":8, "variant":1, "name":"Cramorant", "type":["flying", "water"]},
	{"id":"0846", "gen":8, "variant":1, "name":"Arrokuda", "type":["water"]},
	{"id":"0847", "gen":8, "variant":1, "name":"Barraskewda", "type":["water"]},
	{"id":"0848", "gen":8, "variant":1, "name":"Toxel", "type":["electric", "poison"]},
	{"id":"0849", "gen":8, "variant":1, "name":"Toxtricity", "type":["electric", "poison"]},
	{"id":"0850", "gen":8, "variant":1, "name":"Sizzlipede", "type":["fire", "bug"]},
	{"id":"0851", "gen":8, "variant":1, "name":"Centiskorch", "type":["fire", "bug"]},
	{"id":"0852", "gen":8, "variant":1, "name":"Clobbopus", "type":["fighting"]},
	{"id":"0853", "gen":8, "variant":1, "name":"Grapploct", "type":["fighting"]},
	{"id":"0854", "gen":8, "variant":1, "name":"Sinistea", "type":["ghost"]},
	{"id":"0855", "gen":8, "variant":1, "name":"Polteageist", "type":["ghost"]},
	{"id":"0856", "gen":8, "variant":1, "name":"Hatenna", "type":["psychic"]},
	{"id":"0857", "gen":8, "variant":1, "name":"Hattrem", "type":["psychic"]},
	{"id":"0858", "gen":8, "variant":1, "name":"Hatterene", "type":["psychic", "fairy"]},
	{"id":"0859", "gen":8, "variant":1, "name":"Impidimp", "type":["dark", "fairy"]},
	{"id":"0860", "gen":8, "variant":1, "name":"Morgrem", "type":["dark", "fairy"]},
	{"id":"0861", "gen":8, "variant":1, "name":"Grimmsnarl", "type":["dark", "fairy"]},
	{"id":"0862", "gen":8, "variant":1, "name":"Obstagoon", "type":["dark", "normal"]},
	{"id":"0863", "gen":8, "variant":1, "name":"Perrserker", "type":["steel"]},
	{"id":"0864", "gen":8, "variant":1, "name":"Cursola", "type":["ghost"]},
	{"id":"0865", "gen":8, "variant":1, "name":"Sirfetch’d", "type":["fighting"]},
	{"id":"0866", "gen":8, "variant":1, "name":"Mr. Rime", "type":["ice", "psychic"]},
	{"id":"0867", "gen":8, "variant":1, "name":"Runerigus", "type":["ground", "ghost"]},
	{"id":"0868", "gen":8, "variant":1, "name":"Milcery", "type":["fairy"]},
	{"id":"0869", "gen":8, "variant":1, "name":"Alcremie", "type":["fairy"]},
	{"id":"0870", "gen":8, "variant":1, "name":"Falinks", "type":["fighting"]},
	{"id":"0871", "gen":8, "variant":1, "name":"Pincurchin", "type":["electric"]},
	{"id":"0872", "gen":8, "variant":1, "name":"Snom", "type":["ice", "bug"]},
	{"id":"0873", "gen":8, "variant":1, "name":"Frosmoth", "type":["ice", "bug"]},
	{"id":"0874", "gen":8, "variant":1, "name":"Stonjourner", "type":["rock"]},
	{"id":"0875", "gen":8, "variant":1, "name":"Eiscue", "type":["ice"]},
	{"id":"0876", "gen":8, "variant":1, "name":"Indeedee", "type":["psychic", "normal"]},
	{"id":"0877", "gen":8, "variant":1, "name":"Morpeko", "type":["electric", "dark"]},
	{"id":"0878", "gen":8, "variant":1, "name":"Cufant", "type":["steel"]},
	{"id":"0879", "gen":8, "variant":1, "name":"Copperajah", "type":["steel"]},
	{"id":"0880", "gen":8, "variant":1, "name":"Dracozolt", "type":["electric", "dragon"]},
	{"id":"0881", "gen":8, "variant":1, "name":"Arctozolt", "type":["electric", "ice"]},
	{"id":"0882", "gen":8, "variant":1, "name":"Dracovish", "type":["water", "dragon"]},
	{"id":"0883", "gen":8, "variant":1, "name":"Arctovish", "type":["water", "ice"]},
	{"id":"0884", "gen":8, "variant":1, "name":"Duraludon", "type":["steel", "dragon"]},
	{"id":"0885", "gen":8, "variant":1, "name":"Dreepy", "type":["dragon", "ghost"]},
	{"id":"0886", "gen":8, "variant":1, "name":"Drakloak", "type":["dragon", "ghost"]},
	{"id":"0887", "gen":8, "variant":1, "name":"Dragapult", "type":["dragon", "ghost"]},
	{"id":"0888", "gen":8, "variant":1, "name":"Zacian (Guerrero Avezado)", "type":["fairy"], "special":"legendary"},
	{"id":"0888", "gen":8, "variant":2, "name":"Zacian (Espada Suprema)", "type":["fairy", "steel"], "special":"legendary"},
	{"id":"0889", "gen":8, "variant":1, "name":"Zamazenta (Guerrero Avezado)", "type":["fighting"], "special":"legendary"},
	{"id":"0889", "gen":8, "variant":2, "name":"Zamazenta (Escudo Supremo)", "type":["fighting", "steel"], "special":"legendary"},
	{"id":"0890", "gen":8, "variant":1, "name":"Eternatus", "type":["poison", "dragon"], "special":"legendary"},
	{"id":"0891", "gen":8, "variant":1, "name":"Kubfu", "type":["fighting"], "special":"legendary"},
	{"id":"0892", "gen":8, "variant":1, "name":"Urshifu", "type":["fighting", "dark"], "special":"legendary"},
	{"id":"0893", "gen":8, "variant":1, "name":"Zarude", "type":["dark", "grass"], "special":"legendary"},
	{"id":"0894", "gen":8, "variant":1, "name":"Regieleki", "type":["electric"], "special":"legendary"},
	{"id":"0895", "gen":8, "variant":1, "name":"Regidrago", "type":["dragon"], "special":"legendary"},
	{"id":"0896", "gen":8, "variant":1, "name":"Glastrier", "type":["ice"], "special":"legendary"},
	{"id":"0897", "gen":8, "variant":1, "name":"Spectrier", "type":["ghost"], "special":"legendary"},
	{"id":"0898", "gen":8, "variant":1, "name":"Calyrex", "type":["psychic", "grass"], "special":"legendary"},
	{"id":"0899", "gen":8, "variant":1, "name":"Wyrdeer", "type":["normal", "psychic"]},
	{"id":"0900", "gen":8, "variant":1, "name":"Kleavor", "type":["bug", "rock"]},
	{"id":"0901", "gen":8, "variant":1, "name":"Ursaluna", "type":["ground", "normal"]},
	{"id":"0902", "gen":8, "variant":1, "name":"Basculegion (Macho)", "type":["water", "ghost"]},
	{"id":"0902", "gen":8, "variant":2, "name":"Basculegion (Hembra)", "type":["water", "ghost"]},
	{"id":"0903", "gen":8, "variant":1, "name":"Sneasler", "type":["fighting", "poison"]},
	{"id":"0904", "gen":8, "variant":1, "name":"Overqwil", "type":["dark", "poison"]},
	{"id":"0905", "gen":8, "variant":1, "name":"Enamorus (Avatar)", "type":["fairy", "flying"], "special":"legendary"},
	{"id":"0905", "gen":8, "variant":2, "name":"Enamorus (Totem)", "type":["fairy", "flying"], "special":"legendary"},

	{"id":"0906", "gen":9, "variant":1, "name":"Sprigatito", "type":["grass"], "special":"starter"},
	{"id":"0907", "gen":9, "variant":1, "name":"Floragato", "type":["grass"]},
	{"id":"0908", "gen":9, "variant":1, "name":"Meowscarada", "type":["grass", "dark"]},
	{"id":"0909", "gen":9, "variant":1, "name":"Fuecoco", "type":["fire"], "special":"starter"},
	{"id":"0910", "gen":9, "variant":1, "name":"Crocalor", "type":["fire"]},
	{"id":"0911", "gen":9, "variant":1, "name":"Skeledirge", "type":["fire", "ghost"]},
	{"id":"0912", "gen":9, "variant":1, "name":"Quaxly", "type":["water"], "special":"starter"},
	{"id":"0913", "gen":9, "variant":1, "name":"Quaxwell", "type":["water"]},
	{"id":"0914", "gen":9, "variant":1, "name":"Quaquaval", "type":["water", "fighting"]},
	{"id":"0915", "gen":9, "variant":1, "name":"Lechonk", "type":["normal"]},
	{"id":"0916", "gen":9, "variant":1, "name":"Oinkologne", "type":["normal"]},
	{"id":"0917", "gen":9, "variant":1, "name":"Tarountula", "type":["bug"]},
	{"id":"0918", "gen":9, "variant":1, "name":"Spidops", "type":["bug"]},
	{"id":"0919", "gen":9, "variant":1, "name":"Nymble", "type":["bug"]},
	{"id":"0920", "gen":9, "variant":1, "name":"Lokix", "type":["bug", "dark"]},
	{"id":"0921", "gen":9, "variant":1, "name":"Pawmi", "type":["electric"]},
	{"id":"0922", "gen":9, "variant":1, "name":"Pawmo", "type":["electric", "fighting"]},
	{"id":"0923", "gen":9, "variant":1, "name":"Pawmot", "type":["electric", "fighting"]},
	{"id":"0924", "gen":9, "variant":1, "name":"Tandemaus", "type":["normal"]},
	{"id":"0925", "gen":9, "variant":1, "name":"Maushold", "type":["normal"]},
	{"id":"0926", "gen":9, "variant":1, "name":"Fidough", "type":["fairy"]},
	{"id":"0927", "gen":9, "variant":1, "name":"Dachsbun", "type":["fairy"]},
	{"id":"0928", "gen":9, "variant":1, "name":"Smoliv", "type":["grass", "normal"]},
	{"id":"0929", "gen":9, "variant":1, "name":"Dolliv", "type":["grass", "normal"]},
	{"id":"0930", "gen":9, "variant":1, "name":"Arboliva", "type":["grass", "normal"]},
	{"id":"0931", "gen":9, "variant":1, "name":"Squawkabilly", "type":["normal", "flying"]},
	{"id":"0932", "gen":9, "variant":1, "name":"Nacli", "type":["rock"]},
	{"id":"0933", "gen":9, "variant":1, "name":"Naclstack", "type":["rock"]},
	{"id":"0934", "gen":9, "variant":1, "name":"Garganacl", "type":["rock"]},
	{"id":"0935", "gen":9, "variant":1, "name":"Charcadet", "type":["fire"]},
	{"id":"0936", "gen":9, "variant":1, "name":"Armarouge", "type":["fire", "psychic"]},
	{"id":"0937", "gen":9, "variant":1, "name":"Ceruledge", "type":["fire", "ghost"]},
	{"id":"0938", "gen":9, "variant":1, "name":"Tadbulb", "type":["electric"]},
	{"id":"0939", "gen":9, "variant":1, "name":"Bellibolt", "type":["electric"]},
	{"id":"0940", "gen":9, "variant":1, "name":"Wattrel", "type":["electric", "flying"]},
	{"id":"0941", "gen":9, "variant":1, "name":"Kilowattrel", "type":["electric", "flying"]},
	{"id":"0942", "gen":9, "variant":1, "name":"Maschiff", "type":["dark"]},
	{"id":"0943", "gen":9, "variant":1, "name":"Mabosstiff", "type":["dark"]},
	{"id":"0944", "gen":9, "variant":1, "name":"Shroodle", "type":["poison", "normal"]},
	{"id":"0945", "gen":9, "variant":1, "name":"Grafaiai", "type":["poison", "normal"]},
	{"id":"0946", "gen":9, "variant":1, "name":"Bramblin", "type":["grass", "ghost"]},
	{"id":"0947", "gen":9, "variant":1, "name":"Brambleghast", "type":["grass", "ghost"]},
	{"id":"0948", "gen":9, "variant":1, "name":"Toedscool", "type":["ground", "grass"]},
	{"id":"0949", "gen":9, "variant":1, "name":"Toedscruel", "type":["ground", "grass"]},
	{"id":"0950", "gen":9, "variant":1, "name":"Klawf", "type":["rock"]},
	{"id":"0951", "gen":9, "variant":1, "name":"Capsakid", "type":["grass"]},
	{"id":"0952", "gen":9, "variant":1, "name":"Scovillain", "type":["grass", "fire"]},
	{"id":"0953", "gen":9, "variant":1, "name":"Rellor", "type":["bug"]},
	{"id":"0954", "gen":9, "variant":1, "name":"Rabsca", "type":["bug", "psychic"]},
	{"id":"0955", "gen":9, "variant":1, "name":"Flittle", "type":["psychic"]},
	{"id":"0956", "gen":9, "variant":1, "name":"Espathra", "type":["psychic"]},
	{"id":"0957", "gen":9, "variant":1, "name":"Tinkatink", "type":["fairy", "steel"]},
	{"id":"0958", "gen":9, "variant":1, "name":"Tinkatuff", "type":["fairy", "steel"]},
	{"id":"0959", "gen":9, "variant":1, "name":"Tinkaton", "type":["fairy", "steel"]},
	{"id":"0960", "gen":9, "variant":1, "name":"Wiglett", "type":["water"]},
	{"id":"0961", "gen":9, "variant":1, "name":"Wugtrio", "type":["water"]},
	{"id":"0962", "gen":9, "variant":1, "name":"Bombirdier", "type":["flying", "dark"]},
	{"id":"0963", "gen":9, "variant":1, "name":"Finizen", "type":["water"]},
	{"id":"0964", "gen":9, "variant":1, "name":"Palafin", "type":["water"]},
	{"id":"0965", "gen":9, "variant":1, "name":"Varoom", "type":["steel", "poison"]},
	{"id":"0966", "gen":9, "variant":1, "name":"Revavroom", "type":["steel", "poison"]},
	{"id":"0967", "gen":9, "variant":1, "name":"Cyclizar", "type":["dragon", "normal"]},
	{"id":"0968", "gen":9, "variant":1, "name":"Orthworm", "type":["steel"]},
	{"id":"0969", "gen":9, "variant":1, "name":"Glimmet", "type":["rock", "poison"]},
	{"id":"0970", "gen":9, "variant":1, "name":"Glimmora", "type":["rock", "poison"]},
	{"id":"0971", "gen":9, "variant":1, "name":"Greavard", "type":["ghost"]},
	{"id":"0972", "gen":9, "variant":1, "name":"Houndstone", "type":["ghost"]},
	{"id":"0973", "gen":9, "variant":1, "name":"Flamigo", "type":["flying", "fighting"]},
	{"id":"0974", "gen":9, "variant":1, "name":"Cetoddle", "type":["ice"]},
	{"id":"0975", "gen":9, "variant":1, "name":"Cetitan", "type":["ice"]},
	{"id":"0976", "gen":9, "variant":1, "name":"Veluza", "type":["water", "psychic"]},
	{"id":"0977", "gen":9, "variant":1, "name":"Dondozo", "type":["water"]},
	{"id":"0978", "gen":9, "variant":1, "name":"Tatsugiri", "type":["dragon", "water"]},
	{"id":"0979", "gen":9, "variant":1, "name":"Annihilape", "type":["fighting", "ghost"]},
	{"id":"0980", "gen":9, "variant":1, "name":"Clodsire", "type":["poison", "ground"]},
	{"id":"0981", "gen":9, "variant":1, "name":"Farigiraf", "type":["normal", "psychic"]},
	{"id":"0982", "gen":9, "variant":1, "name":"Dudunsparce", "type":["normal"]},
	{"id":"0983", "gen":9, "variant":1, "name":"Kingambit", "type":["dark", "steel"]},
	{"id":"0984", "gen":9, "variant":1, "name":"Colmilargo", "type":["ground", "fighting"]},
	{"id":"0985", "gen":9, "variant":1, "name":"Colagrito", "type":["fairy", "psychic"]},
	{"id":"0986", "gen":9, "variant":1, "name":"Furioseta", "type":["grass", "dark"]},
	{"id":"0987", "gen":9, "variant":1, "name":"Melenaleteo", "type":["ghost", "fairy"]},
	{"id":"0988", "gen":9, "variant":1, "name":"Reptalada", "type":["bug", "fighting"]},
	{"id":"0989", "gen":9, "variant":1, "name":"Pelarena", "type":["electric", "ground"]},
	{"id":"0990", "gen":9, "variant":1, "name":"Ferrodada", "type":["ground", "steel"]},
	{"id":"0991", "gen":9, "variant":1, "name":"Ferrosaco", "type":["ice", "water"]},
	{"id":"0992", "gen":9, "variant":1, "name":"Ferropalmas", "type":["fighting", "electric"]},
	{"id":"0993", "gen":9, "variant":1, "name":"Ferrocuello", "type":["dark", "flying"]},
	{"id":"0994", "gen":9, "variant":1, "name":"Ferropolilla", "type":["fire", "poison"]},
	{"id":"0995", "gen":9, "variant":1, "name":"Ferropúas", "type":["rock", "electric"]},
	{"id":"0996", "gen":9, "variant":1, "name":"Frigibax", "type":["dragon", "ice"]},
	{"id":"0997", "gen":9, "variant":1, "name":"Arctibax", "type":["dragon", "ice"]},
	{"id":"0998", "gen":9, "variant":1, "name":"Baxcalibur", "type":["dragon", "ice"]},
	{"id":"0999", "gen":9, "variant":1, "name":"Gimmighoul", "type":["ghost"]},
	{"id":"1000", "gen":9, "variant":1, "name":"Gholdengo", "type":["steel", "ghost"]},
	{"id":"1001", "gen":9, "variant":1, "name":"Wo-Chien", "type":["dark", "grass"], "special":"legendary"},
	{"id":"1002", "gen":9, "variant":1, "name":"Chien-Pao", "type":["dark", "ice"], "special":"legendary"},
	{"id":"1003", "gen":9, "variant":1, "name":"Ting-Lu", "type":["dark", "ground"], "special":"legendary"},
	{"id":"1004", "gen":9, "variant":1, "name":"Chi-Yu", "type":["dark", "fire"], "special":"legendary"},
	{"id":"1005", "gen":9, "variant":1, "name":"Bramaluna", "type":["dragon", "dark"]},
	{"id":"1006", "gen":9, "variant":1, "name":"Ferropaladín", "type":["fairy", "fighting"]},
	{"id":"1007", "gen":9, "variant":1, "name":"Koraidon", "type":["fighting", "dragon"], "special":"legendary"},
	{"id":"1008", "gen":9, "variant":1, "name":"Miraidon", "type":["electric", "dragon"], "special":"legendary"}
]
